{
    "__CLASS__": "Adzuna::API::Response::JobSearchResults",
    "mean": 1904645.06,
    "results": [
        {
            "id": "5577433576",
            "description": "Software Senior Engineer The Data Protection Software Engineering team delivers next-generation data protection and data availability enhancements and new products for a changing world. Working at the cutting edge, we design and develop software for to protect data hosted across On-Prem, Public Cloud, Hybrid Cloud - all with the most advanced technologies, tools, software engineering methodologies and the collaboration of internal and external partners. Join us as a Software Senior Engineer on …",
            "title": "Software Senior Engineer",
            "__CLASS__": "Adzuna::API::Response::Job",
            "category": {
                "__CLASS__": "Adzuna::API::Response::Category",
                "label": "IT Jobs",
                "tag": "it-jobs"
            },
            "redirect_url": "https://www.adzuna.in/details/5577433576?utm_medium=api&utm_source=d58ac19b",
            "location": {
                "display_name": "Bangalore, Karnataka",
                "area": [
                    "India",
                    "Karnataka",
                    "Bangalore"
                ],
                "__CLASS__": "Adzuna::API::Response::Location"
            },
            "company": {
                "display_name": "DELL",
                "__CLASS__": "Adzuna::API::Response::Company"
            },
            "salary_is_predicted": "0",
            "created": "2026-01-10T10:35:45Z",
            "contract_time": "full_time",
            "adref": "eyJhbGciOiJIUzI1NiJ9.eyJpIjoiNTU3NzQzMzU3NiIsInMiOiJ1cW1wVnVQdDhCR0R4TDluVEJ6aFp3In0.hAzlRnDZSssYOOC4lb8QdvMxR94xxi8wjVg9ys0GPhU"
        },
        {
            "adref": "eyJhbGciOiJIUzI1NiJ9.eyJpIjoiNTU3NzQzMzU3OCIsInMiOiJ1cW1wVnVQdDhCR0R4TDluVEJ6aFp3In0.-QUrzZ5knzCSwgq4X-3_B0JO3_XyBSv30Mt7McQ3f5k",
            "created": "2026-01-10T10:35:45Z",
            "contract_time": "full_time",
            "company": {
                "__CLASS__": "Adzuna::API::Response::Company",
                "display_name": "DELL"
            },
            "salary_is_predicted": "0",
            "location": {
                "area": [
                    "India",
                    "Karnataka",
                    "Bangalore"
                ],
                "display_name": "Bangalore, Karnataka",
                "__CLASS__": "Adzuna::API::Response::Location"
            },
            "redirect_url": "https://www.adzuna.in/details/5577433578?utm_medium=api&utm_source=d58ac19b",
            "description": "Senior Software Engineer The Software Engineering team delivers next-generation application enhancements and new products for a changing world. Working at the cutting edge, we design and develop software for platforms, peripherals, applications and diagnostics — all with the most advanced technologies, tools, software engineering methodologies and the collaboration of internal and external partners. Join us as a Software Quality Senior Engineer on our Software Quality Engineering team in Bangal…",
            "title": "Software Senior Engineer",
            "__CLASS__": "Adzuna::API::Response::Job",
            "category": {
                "tag": "it-jobs",
                "label": "IT Jobs",
                "__CLASS__": "Adzuna::API::Response::Category"
            },
            "id": "5577433578"
        },
        {
            "redirect_url": "https://www.adzuna.in/details/5577433571?utm_medium=api&utm_source=d58ac19b",
            "id": "5577433571",
            "__CLASS__": "Adzuna::API::Response::Job",
            "category": {
                "label": "IT Jobs",
                "tag": "it-jobs",
                "__CLASS__": "Adzuna::API::Response::Category"
            },
            "description": "Software Senior Engineer The Data Protection Software Engineering team delivers next-generation data protection and data availability enhancements and new products for a changing world. Working at the cutting edge, we design and develop software for to protect data hosted across On-Prem, Public Cloud, Hybrid Cloud - all with the most advanced technologies, tools, software engineering methodologies and the collaboration of internal and external partners. Join us as a Software Senior Engineer on …",
            "title": "Software Senior Engineer",
            "contract_time": "full_time",
            "created": "2026-01-10T10:35:45Z",
            "adref": "eyJhbGciOiJIUzI1NiJ9.eyJzIjoidXFtcFZ1UHQ4QkdEeEw5blRCemhadyIsImkiOiI1NTc3NDMzNTcxIn0.f5OURO-aiE_p7gxwjzgILfOm5r5gaI8sgY-VXo2NgLc",
            "latitude": 18.5062,
            "location": {
                "__CLASS__": "Adzuna::API::Response::Location",
                "area": [
                    "India",
                    "Maharashtra",
                    "Pune"
                ],
                "display_name": "Pune, Maharashtra"
            },
            "longitude": 73.84735,
            "company": {
                "display_name": "DELL",
                "__CLASS__": "Adzuna::API::Response::Company"
            },
            "salary_is_predicted": "0"
        },
        {
            "salary_is_predicted": "0",
            "company": {
                "display_name": "DELL",
                "__CLASS__": "Adzuna::API::Response::Company"
            },
            "latitude": 18.5062,
            "location": {
                "display_name": "Pune, Maharashtra",
                "area": [
                    "India",
                    "Maharashtra",
                    "Pune"
                ],
                "__CLASS__": "Adzuna::API::Response::Location"
            },
            "longitude": 73.84735,
            "adref": "eyJhbGciOiJIUzI1NiJ9.eyJpIjoiNTU3NzQzMzU3MyIsInMiOiJ1cW1wVnVQdDhCR0R4TDluVEJ6aFp3In0.KxL6Di2NyAGF0xWIRbnK_e85My1GAinYHS7qe-86WRk",
            "contract_time": "full_time",
            "created": "2026-01-10T10:35:45Z",
            "category": {
                "__CLASS__": "Adzuna::API::Response::Category",
                "label": "IT Jobs",
                "tag": "it-jobs"
            },
            "__CLASS__": "Adzuna::API::Response::Job",
            "title": "Software Principal Engineer",
            "description": "Software Principal Engineer The Data Protection Software Engineering team delivers next-generation data protection and data availability enhancements and new products for a changing world. Working at the cutting edge, we design and develop software for to protect data hosted across On-Prem, Public Cloud, Hybrid Cloud - all with the most advanced technologies, tools, software engineering methodologies and the collaboration of internal and external partners. Join us as a Software Principal Engine…",
            "id": "5577433573",
            "redirect_url": "https://www.adzuna.in/details/5577433573?utm_medium=api&utm_source=d58ac19b"
        },
        {
            "id": "5577433574",
            "title": "Software Engineer 2",
            "description": "Software Engineer 2 The Data Protection Software Engineering team delivers next-generation data protection and data availability enhancements and new products for a changing world. Working at the cutting edge, we design and develop software to protect data hosted across On-Prem, Public Cloud, Hybrid Cloud - all with the most advanced technologies, tools, software engineering methodologies and the collaboration of internal and external partners. Join us as a Software Engineer 2 on our Engineerin…",
            "__CLASS__": "Adzuna::API::Response::Job",
            "category": {
                "label": "IT Jobs",
                "tag": "it-jobs",
                "__CLASS__": "Adzuna::API::Response::Category"
            },
            "redirect_url": "https://www.adzuna.in/details/5577433574?utm_medium=api&utm_source=d58ac19b",
            "location": {
                "display_name": "Bangalore, Karnataka",
                "area": [
                    "India",
                    "Karnataka",
                    "Bangalore"
                ],
                "__CLASS__": "Adzuna::API::Response::Location"
            },
            "salary_is_predicted": "0",
            "company": {
                "display_name": "DELL",
                "__CLASS__": "Adzuna::API::Response::Company"
            },
            "created": "2026-01-10T10:35:45Z",
            "contract_time": "full_time",
            "adref": "eyJhbGciOiJIUzI1NiJ9.eyJpIjoiNTU3NzQzMzU3NCIsInMiOiJ1cW1wVnVQdDhCR0R4TDluVEJ6aFp3In0.YhJ_fZh9ORmp7WTurxNzDOMrV2voPLXTsdzxzBnzDkg"
        },
        {
            "salary_is_predicted": "0",
            "company": {
                "display_name": "DELL",
                "__CLASS__": "Adzuna::API::Response::Company"
            },
            "location": {
                "area": [
                    "India",
                    "Karnataka",
                    "Bangalore"
                ],
                "display_name": "Bangalore, Karnataka",
                "__CLASS__": "Adzuna::API::Response::Location"
            },
            "adref": "eyJhbGciOiJIUzI1NiJ9.eyJpIjoiNTU3NzQzMzU3NyIsInMiOiJ1cW1wVnVQdDhCR0R4TDluVEJ6aFp3In0.Kf4YsX9Ds-enXWqr7GB1G78TqrjVMYG2MXwg6gUfoRQ",
            "contract_time": "full_time",
            "created": "2026-01-10T10:35:45Z",
            "category": {
                "__CLASS__": "Adzuna::API::Response::Category",
                "tag": "it-jobs",
                "label": "IT Jobs"
            },
            "__CLASS__": "Adzuna::API::Response::Job",
            "description": "Senior Software Engineer The Software Engineering team delivers next-generation application enhancements and new products for a changing world. Working at the cutting edge, we design and develop software for platforms, peripherals, applications and diagnostics — all with the most advanced technologies, tools, software engineering methodologies and the collaboration of internal and external partners. Join us as a Software Quality Senior Engineer on our Software Quality Engineering team in Bangal…",
            "title": "Software Senior Engineer",
            "id": "5577433577",
            "redirect_url": "https://www.adzuna.in/details/5577433577?utm_medium=api&utm_source=d58ac19b"
        },
        {
            "adref": "eyJhbGciOiJIUzI1NiJ9.eyJzIjoidXFtcFZ1UHQ4QkdEeEw5blRCemhadyIsImkiOiI1NTc3NDMzNTcyIn0.eAGHCs95lkxODDoZsF3xXEEygBo3yqBEhG_V52gipzA",
            "contract_time": "full_time",
            "created": "2026-01-10T10:35:45Z",
            "company": {
                "__CLASS__": "Adzuna::API::Response::Company",
                "display_name": "DELL"
            },
            "salary_is_predicted": "0",
            "latitude": 18.5062,
            "longitude": 73.84735,
            "location": {
                "area": [
                    "India",
                    "Maharashtra",
                    "Pune"
                ],
                "display_name": "Pune, Maharashtra",
                "__CLASS__": "Adzuna::API::Response::Location"
            },
            "redirect_url": "https://www.adzuna.in/details/5577433572?utm_medium=api&utm_source=d58ac19b",
            "category": {
                "tag": "it-jobs",
                "label": "IT Jobs",
                "__CLASS__": "Adzuna::API::Response::Category"
            },
            "__CLASS__": "Adzuna::API::Response::Job",
            "description": "Software Senior Engineer The Data Protection Software Engineering team delivers next-generation data protection and data availability enhancements and new products for a changing world. Working at the cutting edge, we design and develop software for to protect data hosted across On-Prem, Public Cloud, Hybrid Cloud - all with the most advanced technologies, tools, software engineering methodologies and the collaboration of internal and external partners. Join us as a Software Senior Engineer on …",
            "title": "Software Senior Engineer",
            "id": "5577433572"
        },
        {
            "id": "5577433547",
            "category": {
                "tag": "it-jobs",
                "label": "IT Jobs",
                "__CLASS__": "Adzuna::API::Response::Category"
            },
            "__CLASS__": "Adzuna::API::Response::Job",
            "title": "Software Senior Engineer",
            "description": "Software Senior Engineer The Software Engineering team delivers next-generation software application enhancements and new products for a changing world. Working at the cutting edge , we design and develop software for platforms, peripherals, applications and diagnostics all with the most advanced technologies, tools, software engineering methodologies and the collaboration of internal and external partners. Join us to do the best work of your career and make a profound social impact as a Softwa…",
            "redirect_url": "https://www.adzuna.in/details/5577433547?utm_medium=api&utm_source=d58ac19b",
            "location": {
                "display_name": "Bangalore, Karnataka",
                "area": [
                    "India",
                    "Karnataka",
                    "Bangalore"
                ],
                "__CLASS__": "Adzuna::API::Response::Location"
            },
            "salary_is_predicted": "0",
            "company": {
                "__CLASS__": "Adzuna::API::Response::Company",
                "display_name": "DELL"
            },
            "contract_time": "full_time",
            "created": "2026-01-10T10:35:44Z",
            "adref": "eyJhbGciOiJIUzI1NiJ9.eyJzIjoidXFtcFZ1UHQ4QkdEeEw5blRCemhadyIsImkiOiI1NTc3NDMzNTQ3In0.uliKZXXcE9E8eB7uu6NCk0MulmuYH2jB2bX94hkqyqk"
        },
        {
            "redirect_url": "https://www.adzuna.in/details/5577433555?utm_medium=api&utm_source=d58ac19b",
            "__CLASS__": "Adzuna::API::Response::Job",
            "category": {
                "__CLASS__": "Adzuna::API::Response::Category",
                "tag": "it-jobs",
                "label": "IT Jobs"
            },
            "title": "Software Principal Engineer",
            "description": "Software Principal Engineer The Data Protection Software Engineering team delivers next-generation data protection and data availability enhancements and new products for a changing world. Working at the cutting edge, we design and develop software for to protect data hosted across On-Prem, Public Cloud, Hybrid Cloud - all with the most advanced technologies, tools, software engineering methodologies and the collaboration of internal and external partners. Join us as a Software Principal Engine…",
            "id": "5577433555",
            "adref": "eyJhbGciOiJIUzI1NiJ9.eyJzIjoidXFtcFZ1UHQ4QkdEeEw5blRCemhadyIsImkiOiI1NTc3NDMzNTU1In0.QJFf-GzwP4Hn2sAN7WPHUMNVgCJlDZJE61vZHq_Atto",
            "contract_time": "full_time",
            "created": "2026-01-10T10:35:44Z",
            "salary_is_predicted": "0",
            "company": {
                "__CLASS__": "Adzuna::API::Response::Company",
                "display_name": "DELL"
            },
            "latitude": 18.5062,
            "longitude": 73.84735,
            "location": {
                "display_name": "Pune, Maharashtra",
                "area": [
                    "India",
                    "Maharashtra",
                    "Pune"
                ],
                "__CLASS__": "Adzuna::API::Response::Location"
            }
        },
        {
            "adref": "eyJhbGciOiJIUzI1NiJ9.eyJpIjoiNTU3NzQzMzU1NiIsInMiOiJ1cW1wVnVQdDhCR0R4TDluVEJ6aFp3In0.6k88vmytT6yFUbB4TGrrnEN3UAJopETSked8fzAc3qk",
            "contract_time": "full_time",
            "created": "2026-01-10T10:35:44Z",
            "company": {
                "display_name": "DELL",
                "__CLASS__": "Adzuna::API::Response::Company"
            },
            "salary_is_predicted": "0",
            "location": {
                "area": [
                    "India",
                    "Karnataka",
                    "Bangalore"
                ],
                "display_name": "Bangalore, Karnataka",
                "__CLASS__": "Adzuna::API::Response::Location"
            },
            "redirect_url": "https://www.adzuna.in/details/5577433556?utm_medium=api&utm_source=d58ac19b",
            "__CLASS__": "Adzuna::API::Response::Job",
            "category": {
                "__CLASS__": "Adzuna::API::Response::Category",
                "label": "IT Jobs",
                "tag": "it-jobs"
            },
            "title": "Software Senior Engineer",
            "description": "Senior Software Engineer The Software Engineering team delivers next-generation application enhancements and new products for a changing world. Working at the cutting edge, we design and develop software for platforms, peripherals, applications and diagnostics — all with the most advanced technologies, tools, software engineering methodologies and the collaboration of internal and external partners. Join us to do the best work of your career and make a profound social impact as a Senior Softwar…",
            "id": "5577433556"
        },
        {
            "redirect_url": "https://www.adzuna.in/details/5577433548?utm_medium=api&utm_source=d58ac19b",
            "id": "5577433548",
            "title": "Software Senior Principal Engineer",
            "description": "Senior Principal Software Engineer The Software Engineering team delivers next-generation software application enhancements and new products for a changing world. Working at the cutting edge, we design and develop software for platforms, peripherals, applications and diagnostics — all with the most advanced technologies, tools, software engineering methodologies and the collaboration of internal and external partners. Join us to do the best work of your career and make a profound social impact …",
            "category": {
                "tag": "it-jobs",
                "label": "IT Jobs",
                "__CLASS__": "Adzuna::API::Response::Category"
            },
            "__CLASS__": "Adzuna::API::Response::Job",
            "created": "2026-01-10T10:35:44Z",
            "contract_time": "full_time",
            "adref": "eyJhbGciOiJIUzI1NiJ9.eyJzIjoidXFtcFZ1UHQ4QkdEeEw5blRCemhadyIsImkiOiI1NTc3NDMzNTQ4In0.7oE8Br4QtebdZ98g3iZw6PG6uMUYkwEFJwqm1-mWwW0",
            "location": {
                "__CLASS__": "Adzuna::API::Response::Location",
                "area": [
                    "India",
                    "Karnataka",
                    "Bangalore"
                ],
                "display_name": "Bangalore, Karnataka"
            },
            "salary_is_predicted": "0",
            "company": {
                "__CLASS__": "Adzuna::API::Response::Company",
                "display_name": "DELL"
            }
        },
        {
            "salary_is_predicted": "0",
            "company": {
                "__CLASS__": "Adzuna::API::Response::Company",
                "display_name": "DELL"
            },
            "location": {
                "__CLASS__": "Adzuna::API::Response::Location",
                "display_name": "Bangalore, Karnataka",
                "area": [
                    "India",
                    "Karnataka",
                    "Bangalore"
                ]
            },
            "adref": "eyJhbGciOiJIUzI1NiJ9.eyJpIjoiNTU3NzQzMzU0MiIsInMiOiJ1cW1wVnVQdDhCR0R4TDluVEJ6aFp3In0.81BU8CbWSFIrXdc239eDy83CoNqOfDa9n7BJu0vS-yQ",
            "contract_time": "full_time",
            "created": "2026-01-10T10:35:43Z",
            "category": {
                "tag": "it-jobs",
                "label": "IT Jobs",
                "__CLASS__": "Adzuna::API::Response::Category"
            },
            "__CLASS__": "Adzuna::API::Response::Job",
            "title": "Software Principal Engineer",
            "description": "Software Principal Engineer The Software Engineering team delivers next-generation application enhancements and new products for a changing world. Working at the cutting edge, we design and develop software for platforms, peripherals, applications and diagnostics — all with the most advanced technologies, tools, software engineering methodologies and the collaboration of internal and external partners. Join us to do the best work of your career and make a profound social impact as a Software Pr…",
            "id": "5577433542",
            "redirect_url": "https://www.adzuna.in/details/5577433542?utm_medium=api&utm_source=d58ac19b"
        },
        {
            "redirect_url": "https://www.adzuna.in/details/5577432817?utm_medium=api&utm_source=d58ac19b",
            "salary_max": 1200000,
            "id": "5577432817",
            "__CLASS__": "Adzuna::API::Response::Job",
            "category": {
                "label": "IT Jobs",
                "tag": "it-jobs",
                "__CLASS__": "Adzuna::API::Response::Category"
            },
            "title": "Software Development Engineer Testing (SDET)",
            "description": "Mandatory : - Minimum 2-4 years of experience in *Manual Mobile App Testing* ( Android / iOS) - Minimum work experience of API testing - Ability to pull off releases in a shorter cycle - Work experience with app-based products having 100,000 active users Good to have: - Good mobile testing automation skills - Work experience in a well-known startup - Showcase of issues that you logged in open - apps / bug bounty if you had any Responsibilities : - Review requirements, specifications and technic…",
            "contract_time": "full_time",
            "created": "2026-01-10T10:35:12Z",
            "salary_min": 800000,
            "adref": "eyJhbGciOiJIUzI1NiJ9.eyJzIjoidXFtcFZ1UHQ4QkdEeEw5blRCemhadyIsImkiOiI1NTc3NDMyODE3In0.OYN06eLWL5CfSjJYiVxJSJRw4dgsju-hGWug1_5WM1E",
            "location": {
                "display_name": "Bangalore, Karnataka",
                "area": [
                    "India",
                    "Karnataka",
                    "Bangalore"
                ],
                "__CLASS__": "Adzuna::API::Response::Location"
            },
            "salary_is_predicted": "0",
            "company": {
                "display_name": "DailyRounds/Marrow",
                "__CLASS__": "Adzuna::API::Response::Company"
            }
        },
        {
            "adref": "eyJhbGciOiJIUzI1NiJ9.eyJzIjoidXFtcFZ1UHQ4QkdEeEw5blRCemhadyIsImkiOiI1NTc3NDI5OTkyIn0.o4xSLMuxoAwMj33mcixJvNlZV2TN-NwI8QGlBd9S1Pg",
            "contract_time": "full_time",
            "created": "2026-01-10T10:34:43Z",
            "company": {
                "display_name": "ADCI HYD 13 SEZ",
                "__CLASS__": "Adzuna::API::Response::Company"
            },
            "salary_is_predicted": "0",
            "latitude": 17.40275,
            "longitude": 78.50806,
            "location": {
                "__CLASS__": "Adzuna::API::Response::Location",
                "display_name": "Hyderabad, Telangana",
                "area": [
                    "India",
                    "Telangana",
                    "Hyderabad"
                ]
            },
            "redirect_url": "https://www.adzuna.in/details/5577429992?utm_medium=api&utm_source=d58ac19b",
            "category": {
                "__CLASS__": "Adzuna::API::Response::Category",
                "label": "IT Jobs",
                "tag": "it-jobs"
            },
            "__CLASS__": "Adzuna::API::Response::Job",
            "description": "REALM CORE team in Hyderabad is looking for a Software Support Engineer/DevOps who will act as first level support for all incoming production software application issues in Last Mile network. Amazon transportation encompasses all of the operations that deliver worldwide shipments to and from our fulfillment centers and third party locations. Your solutions will impact our customers directly! This job requires you to constantly hit the ground running and your ability to learn quickly and work o…",
            "title": "Support Engineer III , REALM EPIC",
            "id": "5577429992"
        },
        {
            "salary_is_predicted": "0",
            "company": {
                "__CLASS__": "Adzuna::API::Response::Company",
                "display_name": "ADCI - Karnataka - A66"
            },
            "contract_type": "contract",
            "location": {
                "__CLASS__": "Adzuna::API::Response::Location",
                "area": [
                    "India",
                    "Karnataka",
                    "Bangalore"
                ],
                "display_name": "Bangalore, Karnataka"
            },
            "adref": "eyJhbGciOiJIUzI1NiJ9.eyJzIjoidXFtcFZ1UHQ4QkdEeEw5blRCemhadyIsImkiOiI1NTc3NDMwMDI1In0.mCfI8i2c5_r2tfrRn9v1rcFlVd8lMhaJzxFnXddLoCU",
            "contract_time": "full_time",
            "created": "2026-01-10T10:34:43Z",
            "category": {
                "__CLASS__": "Adzuna::API::Response::Category",
                "tag": "engineering-jobs",
                "label": "Engineering Jobs"
            },
            "__CLASS__": "Adzuna::API::Response::Job",
            "description": "Come and be the pioneer of Amazon NA Supply Chain technology innovation! If you are looking for an opportunity to solve deep technical problems and build innovative solutions in a fast-paced environment while working with smart, passionate business & technical leaders, then this might be the role for you. At Amazon, we are committed to being the most customer-centric company on earth. North America Supply Chain (NASC) Planning & Execution org is comprised of dynamic teams that shape network pla…",
            "title": "Technical Program Manager, Amazon Regulatory and Trade Services (ARTS)",
            "id": "5577430025",
            "redirect_url": "https://www.adzuna.in/details/5577430025?utm_medium=api&utm_source=d58ac19b"
        },
        {
            "category": {
                "tag": "it-jobs",
                "label": "IT Jobs",
                "__CLASS__": "Adzuna::API::Response::Category"
            },
            "__CLASS__": "Adzuna::API::Response::Job",
            "description": "Kindle E-reader is a revolutionary reading device, the 1 best-selling product on all of Amazon, and one of the most innovative and fast growing businesses at Amazon. It is an iconic product and a thriving business adored by customers around the world – but it’s still “day one” in inspiring the world to read more and get more out of reading every day, across all their devices. As a Sr. Technical Program Manager, you will work closely with the Product Management, Software Development Engineering,…",
            "title": "Sr. Technical Program Manager, E-reader Products",
            "id": "5577429952",
            "redirect_url": "https://www.adzuna.in/details/5577429952?utm_medium=api&utm_source=d58ac19b",
            "company": {
                "display_name": "ADCI - Tamil Nadu",
                "__CLASS__": "Adzuna::API::Response::Company"
            },
            "salary_is_predicted": "0",
            "latitude": 13.06041,
            "longitude": 80.24963,
            "location": {
                "area": [
                    "India",
                    "Tamil Nadu",
                    "Chennai"
                ],
                "display_name": "Chennai, Tamil Nadu",
                "__CLASS__": "Adzuna::API::Response::Location"
            },
            "adref": "eyJhbGciOiJIUzI1NiJ9.eyJpIjoiNTU3NzQyOTk1MiIsInMiOiJ1cW1wVnVQdDhCR0R4TDluVEJ6aFp3In0.0s_uygExMCdczQehim2O-ZCTfCr3lXZ0VveJuMf1ls0",
            "contract_time": "full_time",
            "created": "2026-01-10T10:34:43Z"
        },
        {
            "company": {
                "__CLASS__": "Adzuna::API::Response::Company",
                "display_name": "ADCI MAA 12 SEZ"
            },
            "salary_is_predicted": "0",
            "latitude": 13.06041,
            "longitude": 80.24963,
            "location": {
                "area": [
                    "India",
                    "Tamil Nadu",
                    "Chennai"
                ],
                "display_name": "Chennai, Tamil Nadu",
                "__CLASS__": "Adzuna::API::Response::Location"
            },
            "adref": "eyJhbGciOiJIUzI1NiJ9.eyJpIjoiNTU3NzQyOTk2NSIsInMiOiJ1cW1wVnVQdDhCR0R4TDluVEJ6aFp3In0.YpO7gcucA9wv4tp-pkq1XLNMSxZvIBAWrNL66D7S6KQ",
            "contract_time": "full_time",
            "created": "2026-01-10T10:34:43Z",
            "category": {
                "__CLASS__": "Adzuna::API::Response::Category",
                "tag": "it-jobs",
                "label": "IT Jobs"
            },
            "__CLASS__": "Adzuna::API::Response::Job",
            "description": "FireTV Chennai is looking for passionate, hard-working, and talented software engineers who has experience in building innovative, mission critical, high volume cloud systems that powers our world-class content forward experience for millions of customers. As a software engineer in this team, you are expected to design and implement micro cloud services and APIs serving ultra-high volume transactions. Your cloud services and API’s have direct impact to customer experience, be a base for buildin…",
            "title": "Software Dev Engineer II, FireTV",
            "id": "5577429965",
            "redirect_url": "https://www.adzuna.in/details/5577429965?utm_medium=api&utm_source=d58ac19b"
        },
        {
            "title": "Quality Assurance Engineer I, ShipTech QA",
            "description": "Are you passionate about quality and looking for an opportunity to solve & debug complex technical problems and test innovative solutions in a fast paced environment working with smart, passionate team members, this might be the role for you. We are looking for an experienced Quality Assurance Engineer to join our team and make a difference! Who are we? Amazon’s transportation systems get millions of packages to customers worldwide faster and cheaper, while providing world class customer experi…",
            "__CLASS__": "Adzuna::API::Response::Job",
            "category": {
                "tag": "it-jobs",
                "label": "IT Jobs",
                "__CLASS__": "Adzuna::API::Response::Category"
            },
            "id": "5577429892",
            "redirect_url": "https://www.adzuna.in/details/5577429892?utm_medium=api&utm_source=d58ac19b",
            "salary_is_predicted": "0",
            "company": {
                "__CLASS__": "Adzuna::API::Response::Company",
                "display_name": "ADCI HYD 13 SEZ"
            },
            "location": {
                "__CLASS__": "Adzuna::API::Response::Location",
                "display_name": "India",
                "area": [
                    "India"
                ]
            },
            "adref": "eyJhbGciOiJIUzI1NiJ9.eyJpIjoiNTU3NzQyOTg5MiIsInMiOiJ1cW1wVnVQdDhCR0R4TDluVEJ6aFp3In0.Z_tnqoHAutKkNkL69aKlSjXu0cEOd9IHucLFV5KtaBY",
            "created": "2026-01-10T10:34:42Z",
            "contract_time": "full_time"
        },
        {
            "salary_is_predicted": "0",
            "company": {
                "__CLASS__": "Adzuna::API::Response::Company",
                "display_name": "ADCI HYD 13 SEZ"
            },
            "location": {
                "area": [
                    "India",
                    "Telangana",
                    "Hyderabad"
                ],
                "display_name": "Hyderabad, Telangana",
                "__CLASS__": "Adzuna::API::Response::Location"
            },
            "longitude": 78.50806,
            "latitude": 17.40275,
            "adref": "eyJhbGciOiJIUzI1NiJ9.eyJpIjoiNTU3NzQyOTkyMyIsInMiOiJ1cW1wVnVQdDhCR0R4TDluVEJ6aFp3In0.uRyyBdhBTuBlDnBuPsikkdFovOTAMKPmGcyMO94wVaI",
            "created": "2026-01-10T10:34:42Z",
            "contract_time": "full_time",
            "title": "Software Development Engineer, Retail Foundation System",
            "description": "Are you interested in solving unprecedented technological challenges while seeing the direct impact of your work? Amazon's Value Added Services Tech team in Hyderabad, India seeks Software Development Engineers (SDEs) to build our next-generation services platform. This platform will revolutionize how customers buy services with the same ease as products. Our initiative aims to transform Amazon's service offerings through innovative technology solutions. As an SDE, you will design and implement…",
            "category": {
                "tag": "it-jobs",
                "label": "IT Jobs",
                "__CLASS__": "Adzuna::API::Response::Category"
            },
            "__CLASS__": "Adzuna::API::Response::Job",
            "id": "5577429923",
            "redirect_url": "https://www.adzuna.in/details/5577429923?utm_medium=api&utm_source=d58ac19b"
        },
        {
            "salary_is_predicted": "0",
            "company": {
                "display_name": "Amazon Dev Center India - Hyderabad",
                "__CLASS__": "Adzuna::API::Response::Company"
            },
            "latitude": 17.40275,
            "longitude": 78.50806,
            "location": {
                "area": [
                    "India",
                    "Telangana",
                    "Hyderabad"
                ],
                "display_name": "Hyderabad, Telangana",
                "__CLASS__": "Adzuna::API::Response::Location"
            },
            "adref": "eyJhbGciOiJIUzI1NiJ9.eyJzIjoidXFtcFZ1UHQ4QkdEeEw5blRCemhadyIsImkiOiI1NTc3NDI5OTAyIn0.a1eOjjXUVo3BILDkmzlm-Y47wcsN6zzd_jp0nxCl_8g",
            "contract_time": "full_time",
            "created": "2026-01-10T10:34:42Z",
            "category": {
                "__CLASS__": "Adzuna::API::Response::Category",
                "tag": "it-jobs",
                "label": "IT Jobs"
            },
            "__CLASS__": "Adzuna::API::Response::Job",
            "description": "Are you passionate about building systems that protect millions of customers and developers? Join the Appstore Commerce Fraud & Abuse Prevention team as a Software Development Manager, where you'll lead the charge in safeguarding Amazon Appstore's digital commerce business. In this role, you'll lead a team of talented engineers developing and maintaining sophisticated fraud detection and prevention mechanisms that minimize losses for both our third-party developer partners and Amazon. Your team…",
            "title": "Software Development Manager, Appstore Commerce Fraud & Abuse Prevention",
            "id": "5577429902",
            "redirect_url": "https://www.adzuna.in/details/5577429902?utm_medium=api&utm_source=d58ac19b"
        },
        {
            "salary_is_predicted": "0",
            "company": {
                "display_name": "ADCI - BLR 14 SEZ",
                "__CLASS__": "Adzuna::API::Response::Company"
            },
            "location": {
                "__CLASS__": "Adzuna::API::Response::Location",
                "display_name": "Bangalore, Karnataka",
                "area": [
                    "India",
                    "Karnataka",
                    "Bangalore"
                ]
            },
            "adref": "eyJhbGciOiJIUzI1NiJ9.eyJpIjoiNTU3NzQyOTg0MCIsInMiOiJ1cW1wVnVQdDhCR0R4TDluVEJ6aFp3In0.EOlyOW8IugRy8SQmz0yTR57gcxDKdXygtR7-0NNTyGI",
            "created": "2026-01-10T10:34:42Z",
            "contract_time": "full_time",
            "description": "Do you want to develop software that will power leading edge, next generation mobile and entertainment devices? We invite you to join us in this rare opportunity of building the future of apps and highly-scalable, distributed systems to support those experiences. Key job responsibilities As a Software Development Engineer, you will engage with an experienced cross-disciplinary staff to conceive, design and implement innovative consumer products. You will have an enormous opportunity to make a l…",
            "title": "Software Development Engineer, Appstore, Appstore",
            "category": {
                "__CLASS__": "Adzuna::API::Response::Category",
                "tag": "it-jobs",
                "label": "IT Jobs"
            },
            "__CLASS__": "Adzuna::API::Response::Job",
            "id": "5577429840",
            "redirect_url": "https://www.adzuna.in/details/5577429840?utm_medium=api&utm_source=d58ac19b"
        },
        {
            "created": "2026-01-10T10:34:36Z",
            "contract_time": "full_time",
            "adref": "eyJhbGciOiJIUzI1NiJ9.eyJpIjoiNTU3NzQyOTE4MiIsInMiOiJ1cW1wVnVQdDhCR0R4TDluVEJ6aFp3In0.GBLBZFVKZEMZ_ZRimWrIg3e57b8mLkrjMnyxXHsD2WE",
            "location": {
                "__CLASS__": "Adzuna::API::Response::Location",
                "display_name": "Hyderabad, Telangana",
                "area": [
                    "India",
                    "Telangana",
                    "Hyderabad"
                ]
            },
            "longitude": 78.50806,
            "latitude": 17.40275,
            "salary_is_predicted": "0",
            "company": {
                "display_name": "ADSIPL - Telangana",
                "__CLASS__": "Adzuna::API::Response::Company"
            },
            "redirect_url": "https://www.adzuna.in/details/5577429182?utm_medium=api&utm_source=d58ac19b",
            "id": "5577429182",
            "title": "Data Centre Linux & HW Engineer, India, Data Center Operations",
            "description": "AWS Infrastructure Services owns the design, planning, delivery, and operation of all AWS global infrastructure. In other words, we’re the people who keep the cloud running. We support all AWS data centers and all of the servers, storage, networking, power, and cooling equipment that ensure our customers have continual access to the innovation they rely on. We work on the most challenging problems, with thousands of variables impacting the supply chain — and we’re looking for talented people wh…",
            "category": {
                "label": "IT Jobs",
                "tag": "it-jobs",
                "__CLASS__": "Adzuna::API::Response::Category"
            },
            "__CLASS__": "Adzuna::API::Response::Job"
        },
        {
            "salary_is_predicted": "0",
            "company": {
                "display_name": "ADCI - Haryana",
                "__CLASS__": "Adzuna::API::Response::Company"
            },
            "location": {
                "display_name": "India",
                "area": [
                    "India"
                ],
                "__CLASS__": "Adzuna::API::Response::Location"
            },
            "adref": "eyJhbGciOiJIUzI1NiJ9.eyJpIjoiNTU3NzQyOTE0OCIsInMiOiJ1cW1wVnVQdDhCR0R4TDluVEJ6aFp3In0.oq9WgcijhXlI_-X5CL2iUimK7Ur_kM-bmfvTczaqBCw",
            "contract_time": "full_time",
            "created": "2026-01-10T10:34:36Z",
            "__CLASS__": "Adzuna::API::Response::Job",
            "category": {
                "__CLASS__": "Adzuna::API::Response::Category",
                "label": "IT Jobs",
                "tag": "it-jobs"
            },
            "title": "Software Development Engineer II, Amazon",
            "description": "Team: EasyShip, Amazon.in (Central Seller Fulfilment) Location: Gurgaon, HR, India At Amazon, we hire the best minds in technology to innovate and build on behalf of our customers. The focus we have on our customers is why we are one of the world’s most beloved brands – customer obsession is part of our company DNA. Our Software Development Engineers (SDEs) use technology to solve complex problems and get to see the impact of their work first-hand. The challenges SDEs solve for at Amazon are bi…",
            "id": "5577429148",
            "redirect_url": "https://www.adzuna.in/details/5577429148?utm_medium=api&utm_source=d58ac19b"
        },
        {
            "redirect_url": "https://www.adzuna.in/details/5577428378?utm_medium=api&utm_source=d58ac19b",
            "id": "5577428378",
            "__CLASS__": "Adzuna::API::Response::Job",
            "category": {
                "label": "IT Jobs",
                "tag": "it-jobs",
                "__CLASS__": "Adzuna::API::Response::Category"
            },
            "title": "Software Development II",
            "description": "Amazon.com's Risk Management Team has a worldwide reputation as the 1 in eCommerce Fraud Prevention. Trust and Safety of our customers comes first. We thrive on maintaining the highest bar of customer experience while we maintain those tenets. Do you want to join a team that works on internet scale systems, uses cloud computing services, leverages State of The Art technologies and Gen AI tools? The Core Services team owns the charter of evaluating bad actor risk of all kinds (Buyer, Seller, Bra…",
            "contract_time": "full_time",
            "created": "2026-01-10T10:34:30Z",
            "adref": "eyJhbGciOiJIUzI1NiJ9.eyJpIjoiNTU3NzQyODM3OCIsInMiOiJ1cW1wVnVQdDhCR0R4TDluVEJ6aFp3In0.Wrcx8GLS3Ne9awYLnoICZwsI647lgMzH_yhT3IUVSoo",
            "location": {
                "area": [
                    "India",
                    "Karnataka",
                    "Bangalore"
                ],
                "display_name": "Bangalore, Karnataka",
                "__CLASS__": "Adzuna::API::Response::Location"
            },
            "salary_is_predicted": "0",
            "company": {
                "display_name": "ADCI - Karnataka",
                "__CLASS__": "Adzuna::API::Response::Company"
            }
        },
        {
            "salary_is_predicted": "0",
            "company": {
                "__CLASS__": "Adzuna::API::Response::Company",
                "display_name": "ADCI - Karnataka"
            },
            "location": {
                "area": [
                    "India",
                    "Karnataka",
                    "Bangalore"
                ],
                "display_name": "Bangalore, Karnataka",
                "__CLASS__": "Adzuna::API::Response::Location"
            },
            "adref": "eyJhbGciOiJIUzI1NiJ9.eyJpIjoiNTU3NzQyODMwMCIsInMiOiJ1cW1wVnVQdDhCR0R4TDluVEJ6aFp3In0.khFykS_eTmXmwcpXLdmj4ZuCgo1H8fX_Bzqr9L4m06s",
            "created": "2026-01-10T10:34:29Z",
            "contract_time": "full_time",
            "description": "Are you passionate about working with Amazon-scale systems, solving critical engineering problems, and delivering mission critical solutions? Does the idea of building end-to-end financial solutions that will delight Selling Partners excite you? If yes, then we want to talk with you. Selling Partner Financial Technology (SPFT) is looking for a dynamic engineer to join our financial experiences team, to deliver world-class financial experiences that delights our Selling Partners. Selling Partner…",
            "title": "Software Development Engineer",
            "__CLASS__": "Adzuna::API::Response::Job",
            "category": {
                "tag": "it-jobs",
                "label": "IT Jobs",
                "__CLASS__": "Adzuna::API::Response::Category"
            },
            "id": "5577428300",
            "redirect_url": "https://www.adzuna.in/details/5577428300?utm_medium=api&utm_source=d58ac19b"
        },
        {
            "contract_time": "full_time",
            "created": "2026-01-10T10:34:23Z",
            "adref": "eyJhbGciOiJIUzI1NiJ9.eyJzIjoidXFtcFZ1UHQ4QkdEeEw5blRCemhadyIsImkiOiI1NTc3NDI3NjY2In0.JrxSvCRFW_Xb8qUmmBqvUmBSX51azyXPCwbbe9oSlj8",
            "location": {
                "display_name": "Bangalore, Karnataka",
                "area": [
                    "India",
                    "Karnataka",
                    "Bangalore"
                ],
                "__CLASS__": "Adzuna::API::Response::Location"
            },
            "salary_is_predicted": "0",
            "company": {
                "__CLASS__": "Adzuna::API::Response::Company",
                "display_name": "ADCI - Karnataka"
            },
            "redirect_url": "https://www.adzuna.in/details/5577427666?utm_medium=api&utm_source=d58ac19b",
            "id": "5577427666",
            "__CLASS__": "Adzuna::API::Response::Job",
            "category": {
                "tag": "it-jobs",
                "label": "IT Jobs",
                "__CLASS__": "Adzuna::API::Response::Category"
            },
            "title": "Software Development Engineer, Amazon Flex",
            "description": "Amazon’s Last Mile Technology has the operational focus of providing new and different technologies to solve challenges in the last mile delivery space. We want to ensure a top-in-class customer experience from the time a customer places an order on Amazon.com to the time it lands in the customer’s hands. It is in our makeup to drive true innovation in this space. Building on that concept, one of the key delivery systems to support Last Mile is Amazon Flex. Amazon Flex aims to delight customers…"
        },
        {
            "contract_time": "full_time",
            "created": "2026-01-10T10:34:20Z",
            "adref": "eyJhbGciOiJIUzI1NiJ9.eyJpIjoiNTU3NzQyNzMyOSIsInMiOiJ1cW1wVnVQdDhCR0R4TDluVEJ6aFp3In0.s7CMB09HINvIQG1uEFPBE9QWufImXNTNWnc3Xq79YHQ",
            "latitude": 17.40275,
            "longitude": 78.50806,
            "location": {
                "__CLASS__": "Adzuna::API::Response::Location",
                "area": [
                    "India",
                    "Telangana",
                    "Hyderabad"
                ],
                "display_name": "Hyderabad, Telangana"
            },
            "salary_is_predicted": "0",
            "company": {
                "display_name": "ADCI HYD 13 SEZ",
                "__CLASS__": "Adzuna::API::Response::Company"
            },
            "redirect_url": "https://www.adzuna.in/details/5577427329?utm_medium=api&utm_source=d58ac19b",
            "id": "5577427329",
            "__CLASS__": "Adzuna::API::Response::Job",
            "category": {
                "__CLASS__": "Adzuna::API::Response::Category",
                "tag": "it-jobs",
                "label": "IT Jobs"
            },
            "description": "Amazon moves millions of packages every day through the world's largest transportation network of planes, trucks, and delivery vehicles. Before any package can be assigned to a route, someone needs to design that network - figure out which lanes exist, how much capacity each node and lane can handle, and what changes are needed as demand shifts. That's what we build. Global Transportation Tech Services (GTTS) creates software that manages the foundation of Amazon's outbound transportation netwo…",
            "title": "Software Dev Engineer II , Global Transportation Tech Services (GTTS)"
        },
        {
            "description": "Architectural layout annotation and preparation Collect and organize architectural layout drawings. Gather CAD files and 2D drawings from available sources such as portfolios and available drawings datasets, categorize them based on the building type and format. Clean and preprocess layout images. Remove title blocks, legends, and non-layout elements. Enhance contrast and remove noise to create clean, training-ready images. Identify and fix layout quality issues. Document and correct problems s…",
            "title": "Architectural layout annotator",
            "__CLASS__": "Adzuna::API::Response::Job",
            "category": {
                "label": "Engineering Jobs",
                "tag": "engineering-jobs",
                "__CLASS__": "Adzuna::API::Response::Category"
            },
            "id": "5577423460",
            "salary_max": 45,
            "redirect_url": "https://www.adzuna.in/details/5577423460?utm_medium=api&utm_source=d58ac19b",
            "salary_is_predicted": "0",
            "company": {
                "display_name": "Hedral Co",
                "__CLASS__": "Adzuna::API::Response::Company"
            },
            "location": {
                "__CLASS__": "Adzuna::API::Response::Location",
                "area": [
                    "India"
                ],
                "display_name": "India"
            },
            "adref": "eyJhbGciOiJIUzI1NiJ9.eyJpIjoiNTU3NzQyMzQ2MCIsInMiOiJ1cW1wVnVQdDhCR0R4TDluVEJ6aFp3In0.5gtpfzCz7MEQPTDwxL6OwtG6Cs1WnCu-psmE5qxKoQI",
            "salary_min": 5,
            "created": "2026-01-10T10:33:47Z",
            "contract_time": "full_time"
        },
        {
            "id": "5577377233",
            "__CLASS__": "Adzuna::API::Response::Job",
            "category": {
                "label": "IT Jobs",
                "tag": "it-jobs",
                "__CLASS__": "Adzuna::API::Response::Category"
            },
            "title": "Internship Opportunity: Microsoft PowerApps Developer",
            "description": "Internship Opportunity: Power Apps Developer Location: Remote Duration: 6 months About M365Consult M365Consult is committed to innovation and growth by helping clients get the most out of Microsoft 365 and the Power Platform. Joining the team offers hands-on experience in Power Platform development within a fast-growing European Microsoft consulting environment. Role Overview As a Power Apps Developer Intern at M365Consult, you will support the design and development of low-code business applic…",
            "redirect_url": "https://www.adzuna.in/details/5577377233?utm_medium=api&utm_source=d58ac19b",
            "latitude": 12.95703,
            "location": {
                "__CLASS__": "Adzuna::API::Response::Location",
                "display_name": "Bangalore, Karnataka",
                "area": [
                    "India",
                    "Karnataka",
                    "Bangalore"
                ]
            },
            "longitude": 77.59837,
            "company": {
                "display_name": "M365Connect",
                "__CLASS__": "Adzuna::API::Response::Company"
            },
            "salary_is_predicted": "0",
            "contract_type": "contract",
            "created": "2026-01-10T10:01:09Z",
            "adref": "eyJhbGciOiJIUzI1NiJ9.eyJzIjoidXFtcFZ1UHQ4QkdEeEw5blRCemhadyIsImkiOiI1NTc3Mzc3MjMzIn0.SNYwULyFFgHdivK6ZsQFwGm3_7T3hRaIqA85xRXTfZ4"
        },
        {
            "created": "2026-01-10T10:01:09Z",
            "adref": "eyJhbGciOiJIUzI1NiJ9.eyJpIjoiNTU3NzM3NzIyNyIsInMiOiJ1cW1wVnVQdDhCR0R4TDluVEJ6aFp3In0.YRZoJ6-oJilKpjBjXY9ehuKjyRPyhjW7DKR95skyrIs",
            "latitude": 28.62523,
            "location": {
                "__CLASS__": "Adzuna::API::Response::Location",
                "area": [
                    "India",
                    "Delhi"
                ],
                "display_name": "Delhi, India"
            },
            "longitude": 77.224601,
            "salary_is_predicted": "0",
            "company": {
                "display_name": "M365Connect",
                "__CLASS__": "Adzuna::API::Response::Company"
            },
            "contract_type": "contract",
            "redirect_url": "https://www.adzuna.in/details/5577377227?utm_medium=api&utm_source=d58ac19b",
            "id": "5577377227",
            "__CLASS__": "Adzuna::API::Response::Job",
            "category": {
                "label": "IT Jobs",
                "tag": "it-jobs",
                "__CLASS__": "Adzuna::API::Response::Category"
            },
            "description": "Internship Opportunity: Power Apps Developer Location: Remote Duration: 6 months About M365Consult M365Consult is committed to innovation and growth by helping clients get the most out of Microsoft 365 and the Power Platform. Joining the team offers hands-on experience in Power Platform development within a fast-growing European Microsoft consulting environment. Role Overview As a Power Apps Developer Intern at M365Consult, you will support the design and development of low-code business applic…",
            "title": "Internship Opportunity: Microsoft Power Apps Developer"
        },
        {
            "id": "5577369243",
            "title": "QA",
            "description": "About Us Innovate. Create. Elevate . At Vertis, we are on a mission to constantly innovate and create exceptional digital solutions. Our goal is to elevate our clients brands and the experiences they deliver to their customers through the power of technology-driven creativity. Our people are the catalyst, empowering our clients to successfully transform their businesses - join our team of able, confident, and motivated superstars. About the job Are you an experienced QA Engineer with a strong b…",
            "__CLASS__": "Adzuna::API::Response::Job",
            "category": {
                "__CLASS__": "Adzuna::API::Response::Category",
                "tag": "scientific-qa-jobs",
                "label": "Scientific & QA Jobs"
            },
            "redirect_url": "https://www.adzuna.in/details/5577369243?utm_medium=api&utm_source=d58ac19b",
            "longitude": 78.50806,
            "location": {
                "__CLASS__": "Adzuna::API::Response::Location",
                "area": [
                    "India",
                    "Telangana",
                    "Hyderabad"
                ],
                "display_name": "Hyderabad, Telangana"
            },
            "latitude": 17.40275,
            "company": {
                "__CLASS__": "Adzuna::API::Response::Company",
                "display_name": "Vertis Digital"
            },
            "salary_is_predicted": "0",
            "created": "2026-01-10T09:59:10Z",
            "adref": "eyJhbGciOiJIUzI1NiJ9.eyJpIjoiNTU3NzM2OTI0MyIsInMiOiJ1cW1wVnVQdDhCR0R4TDluVEJ6aFp3In0.C9NDeVap54efWEGU4dD3QEfcDWrOGWFDdvt3XCC4zIc"
        },
        {
            "created": "2026-01-10T08:42:53Z",
            "adref": "eyJhbGciOiJIUzI1NiJ9.eyJzIjoidXFtcFZ1UHQ4QkdEeEw5blRCemhadyIsImkiOiI1NTc3Mjc3Nzg5In0.nENHW6tZ0aSho9tq5PtYbsGHuAyh_97CaBgkvoZoblc",
            "location": {
                "__CLASS__": "Adzuna::API::Response::Location",
                "area": [
                    "India"
                ],
                "display_name": "India"
            },
            "salary_is_predicted": "0",
            "company": {
                "display_name": "Ikigai Labs",
                "__CLASS__": "Adzuna::API::Response::Company"
            },
            "redirect_url": "https://www.adzuna.in/details/5577277789?utm_medium=api&utm_source=d58ac19b",
            "id": "5577277789",
            "__CLASS__": "Adzuna::API::Response::Job",
            "category": {
                "label": "IT Jobs",
                "tag": "it-jobs",
                "__CLASS__": "Adzuna::API::Response::Category"
            },
            "description": "We are seeking a Data Engineer who excels in cleaning, transforming, and preparing complex data for integration into machine learning models. In this role, you will work closely with clients to understand their data and ensure it is properly formatted, validated, and optimized for use in our data pipelines. This position emphasizes data hygiene, reconciliation, and transformation—turning raw, messy data into structured, reliable datasets that flow seamlessly through our systems. The ideal candi…",
            "title": "Data Engineer"
        },
        {
            "adref": "eyJhbGciOiJIUzI1NiJ9.eyJpIjoiNTU3NzI3NTQ0MiIsInMiOiJ1cW1wVnVQdDhCR0R4TDluVEJ6aFp3In0.skF_4p6Owyg-q_5W2NzAYnjFOAeCYKLJtadGpcCypiA",
            "created": "2026-01-10T08:39:28Z",
            "contract_time": "full_time",
            "company": {
                "__CLASS__": "Adzuna::API::Response::Company",
                "display_name": "MaxEye Technologies"
            },
            "salary_is_predicted": "0",
            "location": {
                "area": [
                    "India"
                ],
                "display_name": "India",
                "__CLASS__": "Adzuna::API::Response::Location"
            },
            "redirect_url": "https://www.adzuna.in/land/ad/5577275442?se=uqmpVuPt8BGDxL9nTBzhZw&utm_medium=api&utm_source=d58ac19b&v=6C46E3ACFB5A6FFA63BFD9BC377E58AD835645C5",
            "title": "ATE Sr Software Engineer",
            "description": "Senior Software Engineer – ATE Team (6 Years Experience) Location: Pune, Maharashtra Experience: 6 years Job Type: Full-time [Onsite] Team: ATE About the Role: We are seeking a seasoned Senior Software Engineer to lead the development of advanced ATE solutions for Automotive, RF and wireless communication testing. You will play a key role in Project Management, architecture, design, and mentoring junior engineers. Responsibilities: · Architect and develop scalable ATE software solutions. · Lead…",
            "category": {
                "__CLASS__": "Adzuna::API::Response::Category",
                "label": "Engineering Jobs",
                "tag": "engineering-jobs"
            },
            "__CLASS__": "Adzuna::API::Response::Job",
            "id": "5577275442"
        },
        {
            "location": {
                "__CLASS__": "Adzuna::API::Response::Location",
                "area": [
                    "India"
                ],
                "display_name": "India"
            },
            "salary_is_predicted": "0",
            "company": {
                "__CLASS__": "Adzuna::API::Response::Company",
                "display_name": "Krimatix"
            },
            "created": "2026-01-10T08:39:15Z",
            "adref": "eyJhbGciOiJIUzI1NiJ9.eyJzIjoidXFtcFZ1UHQ4QkdEeEw5blRCemhadyIsImkiOiI1NTc3Mjc1Mzg1In0.f343XYoWI0vJfGiLWHqzKMApeaNgVkX5TEtnFczCTwc",
            "id": "5577275385",
            "category": {
                "__CLASS__": "Adzuna::API::Response::Category",
                "label": "IT Jobs",
                "tag": "it-jobs"
            },
            "__CLASS__": "Adzuna::API::Response::Job",
            "title": "Senior Full Stack Developer ( NodeJS  ReactJS  Azure)",
            "description": "Role Summary Krimatix is building a modular, metadata-driven platform for industrial execution, inspection, and integrity workflows. User experiences, validations, and workflows are dynamically generated from JSON configuration and rules. We are seeking five contract Senior Software Engineers who can design and implement end-to-end solutions across frontend, backend, and data. This role requires a strong security mindset and shift-left quality practices, and may also contribute to AI-enabled ca…",
            "redirect_url": "https://www.adzuna.in/land/ad/5577275385?se=uqmpVuPt8BGDxL9nTBzhZw&utm_medium=api&utm_source=d58ac19b&v=191A30B7641B1CBB84F4DCA128A5558A259161DD"
        },
        {
            "salary_is_predicted": "0",
            "company": {
                "__CLASS__": "Adzuna::API::Response::Company",
                "display_name": "Zscaler"
            },
            "latitude": 17.40275,
            "location": {
                "area": [
                    "India",
                    "Telangana",
                    "Hyderabad"
                ],
                "display_name": "Hyderabad, Telangana",
                "__CLASS__": "Adzuna::API::Response::Location"
            },
            "longitude": 78.50806,
            "adref": "eyJhbGciOiJIUzI1NiJ9.eyJzIjoidXFtcFZ1UHQ4QkdEeEw5blRCemhadyIsImkiOiI1NTc3MjczODk5In0.vo-cmZ_--nfHvkRuKxLgtIt9LgK38T_CerMejSQkbnw",
            "created": "2026-01-10T08:35:23Z",
            "__CLASS__": "Adzuna::API::Response::Job",
            "category": {
                "tag": "it-jobs",
                "label": "IT Jobs",
                "__CLASS__": "Adzuna::API::Response::Category"
            },
            "description": "About Zscaler Zscaler accelerates digital transformation so our customers can be more agile, efficient, resilient, and secure. Our cloud native Zero Trust Exchange platform protects thousands of customers from cyberattacks and data loss by securely connecting users, devices, and applications in any location. Here, impact in your role matters more than title and trust is built on results. We believe in transparency and value constructive, honest debate -we're focused on getting to the best ideas…",
            "title": "Staff Software Development Engineer - Golang",
            "id": "5577273899",
            "redirect_url": "https://www.adzuna.in/land/ad/5577273899?se=uqmpVuPt8BGDxL9nTBzhZw&utm_medium=api&utm_source=d58ac19b&v=7FB60BED7F617712E6ACFCCD5FFB45120544261D"
        },
        {
            "adref": "eyJhbGciOiJIUzI1NiJ9.eyJpIjoiNTU3NzI3MzkyMyIsInMiOiJ1cW1wVnVQdDhCR0R4TDluVEJ6aFp3In0.Yae7PD-q4KI3EuBplF7ffXh9hdjw-qjTNIU98K-6VWw",
            "created": "2026-01-10T08:35:23Z",
            "company": {
                "__CLASS__": "Adzuna::API::Response::Company",
                "display_name": "Zscaler"
            },
            "salary_is_predicted": "0",
            "location": {
                "__CLASS__": "Adzuna::API::Response::Location",
                "area": [
                    "India",
                    "Maharashtra",
                    "Pune"
                ],
                "display_name": "Pune, Maharashtra"
            },
            "longitude": 73.84735,
            "latitude": 18.5062,
            "redirect_url": "https://www.adzuna.in/land/ad/5577273923?se=uqmpVuPt8BGDxL9nTBzhZw&utm_medium=api&utm_source=d58ac19b&v=36A24C4A51F85C9EA456E94D8DC2FB80EEAE43EB",
            "title": "Staff Software Development Engineer - Golang",
            "description": "About Zscaler Zscaler accelerates digital transformation so our customers can be more agile, efficient, resilient, and secure. Our cloud native Zero Trust Exchange platform protects thousands of customers from cyberattacks and data loss by securely connecting users, devices, and applications in any location. Here, impact in your role matters more than title and trust is built on results. We believe in transparency and value constructive, honest debate -we're focused on getting to the best ideas…",
            "category": {
                "tag": "it-jobs",
                "label": "IT Jobs",
                "__CLASS__": "Adzuna::API::Response::Category"
            },
            "__CLASS__": "Adzuna::API::Response::Job",
            "id": "5577273923"
        },
        {
            "created": "2026-01-10T08:35:23Z",
            "adref": "eyJhbGciOiJIUzI1NiJ9.eyJzIjoidXFtcFZ1UHQ4QkdEeEw5blRCemhadyIsImkiOiI1NTc3MjczOTI1In0.xGrplpW0yxe9bF7ihRJefolopNKg7Abnh7NKteqtltE",
            "location": {
                "display_name": "Bangalore, Karnataka",
                "area": [
                    "India",
                    "Karnataka",
                    "Bangalore"
                ],
                "__CLASS__": "Adzuna::API::Response::Location"
            },
            "longitude": 77.59837,
            "latitude": 12.95703,
            "salary_is_predicted": "0",
            "company": {
                "__CLASS__": "Adzuna::API::Response::Company",
                "display_name": "Zscaler"
            },
            "redirect_url": "https://www.adzuna.in/land/ad/5577273925?se=uqmpVuPt8BGDxL9nTBzhZw&utm_medium=api&utm_source=d58ac19b&v=B5D46CCB906D113D835EA3DA49D16CB50FFE1BC8",
            "id": "5577273925",
            "description": "About Zscaler Zscaler accelerates digital transformation so our customers can be more agile, efficient, resilient, and secure. Our cloud native Zero Trust Exchange platform protects thousands of customers from cyberattacks and data loss by securely connecting users, devices, and applications in any location. Here, impact in your role matters more than title and trust is built on results. We believe in transparency and value constructive, honest debate -we're focused on getting to the best ideas…",
            "title": "Staff Software Development Engineer - Golang",
            "category": {
                "tag": "it-jobs",
                "label": "IT Jobs",
                "__CLASS__": "Adzuna::API::Response::Category"
            },
            "__CLASS__": "Adzuna::API::Response::Job"
        },
        {
            "redirect_url": "https://www.adzuna.in/land/ad/5577273909?se=uqmpVuPt8BGDxL9nTBzhZw&utm_medium=api&utm_source=d58ac19b&v=98567A700ACA9F82EA43AD75A38F295FCEA780C9",
            "id": "5577273909",
            "category": {
                "__CLASS__": "Adzuna::API::Response::Category",
                "tag": "it-jobs",
                "label": "IT Jobs"
            },
            "__CLASS__": "Adzuna::API::Response::Job",
            "title": "Senior Staff Software Development Engineer",
            "description": "About Zscaler Zscaler accelerates digital transformation so our customers can be more agile, efficient, resilient, and secure. Our cloud native Zero Trust Exchange platform protects thousands of customers from cyberattacks and data loss by securely connecting users, devices, and applications in any location. Here, impact in your role matters more than title and trust is built on results. We believe in transparency and value constructive, honest debate -we're focused on getting to the best ideas…",
            "created": "2026-01-10T08:35:23Z",
            "adref": "eyJhbGciOiJIUzI1NiJ9.eyJzIjoidXFtcFZ1UHQ4QkdEeEw5blRCemhadyIsImkiOiI1NTc3MjczOTA5In0.6MfNBBzaEPdpoe3ZVBXBrukA54fy_ooqgMYcMRgHhYc",
            "latitude": 12.95703,
            "location": {
                "area": [
                    "India",
                    "Karnataka",
                    "Bangalore"
                ],
                "display_name": "Bangalore, Karnataka",
                "__CLASS__": "Adzuna::API::Response::Location"
            },
            "longitude": 77.59837,
            "salary_is_predicted": "0",
            "company": {
                "display_name": "Zscaler",
                "__CLASS__": "Adzuna::API::Response::Company"
            }
        },
        {
            "redirect_url": "https://www.adzuna.in/land/ad/5577273850?se=uqmpVuPt8BGDxL9nTBzhZw&utm_medium=api&utm_source=d58ac19b&v=7DC9B82DB2902D9B0FC8511D8316F9E2B3408AE9",
            "id": "5577273850",
            "title": "Software Engineer II (IN), Senior",
            "description": "Remote Work: Hybrid Overview: At Zebra, we are a community of innovators who come together to create new ways of working. United by curiosity and a culture of caring, we develop smart solutions that anticipate our customer's and partner's needs and solve their challenges. Being a part of Zebra Nation means you are seen, heard, valued, and respected. Drawing from our unique perspectives, we collaborate to deliver on our purpose. Here you are a part of a team pushing boundaries today to redefine …",
            "__CLASS__": "Adzuna::API::Response::Job",
            "category": {
                "__CLASS__": "Adzuna::API::Response::Category",
                "label": "IT Jobs",
                "tag": "it-jobs"
            },
            "created": "2026-01-10T08:35:21Z",
            "adref": "eyJhbGciOiJIUzI1NiJ9.eyJzIjoidXFtcFZ1UHQ4QkdEeEw5blRCemhadyIsImkiOiI1NTc3MjczODUwIn0.HTD8Mc_Foa45SDUzwWIKwoJhyodHGX5_NaPMUdcgC5s",
            "longitude": 77.59837,
            "location": {
                "display_name": "Bangalore, Karnataka",
                "area": [
                    "India",
                    "Karnataka",
                    "Bangalore"
                ],
                "__CLASS__": "Adzuna::API::Response::Location"
            },
            "latitude": 12.95703,
            "company": {
                "display_name": "Zebra Technologies",
                "__CLASS__": "Adzuna::API::Response::Company"
            },
            "salary_is_predicted": "0"
        },
        {
            "id": "5577273631",
            "category": {
                "__CLASS__": "Adzuna::API::Response::Category",
                "label": "Engineering Jobs",
                "tag": "engineering-jobs"
            },
            "__CLASS__": "Adzuna::API::Response::Job",
            "description": "- Build and Lead one of our Back End teams, through execution of product roadmap & program delivery. - Build best of class developer experiences that accelerate product adoption & satisfaction. - Perform architectural, design and hands-on code reviews that raise the bar for the platform. - Demonstrate operational leadership, running the highest-scale critical platform services. - Recruit, on-board and mentor the team. - Hands-on development - up to 50%. - 8 years of Back End Development & at le…",
            "title": "Technical Lead - Software Engineering",
            "redirect_url": "https://www.adzuna.in/land/ad/5577273631?se=uqmpVuPt8BGDxL9nTBzhZw&utm_medium=api&utm_source=d58ac19b&v=46DC1911560400748D09021D2D743EAD011692B9",
            "latitude": 12.95703,
            "longitude": 77.59837,
            "location": {
                "__CLASS__": "Adzuna::API::Response::Location",
                "display_name": "Bangalore, Karnataka",
                "area": [
                    "India",
                    "Karnataka",
                    "Bangalore"
                ]
            },
            "company": {
                "display_name": "Vontier",
                "__CLASS__": "Adzuna::API::Response::Company"
            },
            "salary_is_predicted": "0",
            "created": "2026-01-10T08:35:09Z",
            "adref": "eyJhbGciOiJIUzI1NiJ9.eyJpIjoiNTU3NzI3MzYzMSIsInMiOiJ1cW1wVnVQdDhCR0R4TDluVEJ6aFp3In0.dPcYG5Aut4l44WKobAEgw_agM2h9NJS0XuBECvIs308"
        },
        {
            "adref": "eyJhbGciOiJIUzI1NiJ9.eyJpIjoiNTU3NzI3MzU2MiIsInMiOiJ1cW1wVnVQdDhCR0R4TDluVEJ6aFp3In0.PiqSib41rTzgdb20ZfnBdcvejaLsXNVwlVNTgHL_VU0",
            "created": "2026-01-10T08:35:00Z",
            "salary_is_predicted": "0",
            "company": {
                "display_name": "UnitedHealth Group",
                "__CLASS__": "Adzuna::API::Response::Company"
            },
            "latitude": 12.95703,
            "longitude": 77.59837,
            "location": {
                "__CLASS__": "Adzuna::API::Response::Location",
                "area": [
                    "India",
                    "Karnataka",
                    "Bangalore"
                ],
                "display_name": "Bangalore, Karnataka"
            },
            "redirect_url": "https://www.adzuna.in/land/ad/5577273562?se=uqmpVuPt8BGDxL9nTBzhZw&utm_medium=api&utm_source=d58ac19b&v=5B89F510A3397ACEEE00580F8A5F9CE350BD24B2",
            "__CLASS__": "Adzuna::API::Response::Job",
            "category": {
                "__CLASS__": "Adzuna::API::Response::Category",
                "label": "IT Jobs",
                "tag": "it-jobs"
            },
            "description": "Optum is a global organization that delivers care, aided by technology to help millions of people live healthier lives. The work you do with our team will directly improve health outcomes by connecting people with the care, pharmacy benefits, data and resources they need to feel their best. Here, you will find a culture guided by inclusion, talented peers, comprehensive benefits and career development opportunities. Come make an impact on the communities we serve as you help us advance health o…",
            "title": "Lead Software Engineer",
            "id": "5577273562"
        },
        {
            "redirect_url": "https://www.adzuna.in/land/ad/5577273567?se=uqmpVuPt8BGDxL9nTBzhZw&utm_medium=api&utm_source=d58ac19b&v=5273A7A39E1AC563FCA6EE9B433DF53102963E2A",
            "__CLASS__": "Adzuna::API::Response::Job",
            "category": {
                "label": "IT Jobs",
                "tag": "it-jobs",
                "__CLASS__": "Adzuna::API::Response::Category"
            },
            "title": "Senior Software engineer",
            "description": "Primary Responsibilities:  Software Development:  Design, develop, and maintain scalable, high-performance backend systems using Java and Spring Boot  Implement event-driven architectures using Apache Kafka to ensure real-time data streaming and integration  Develop RESTful APIs and microservices that support front-end applications and business processes  Database Management:  Design and optimize database schemas, queries, and indexes in MySQL or other relational databases  Work with NoSQL data…",
            "id": "5577273567",
            "adref": "eyJhbGciOiJIUzI1NiJ9.eyJzIjoidXFtcFZ1UHQ4QkdEeEw5blRCemhadyIsImkiOiI1NTc3MjczNTY3In0.RNesEB-65Z32blsD-OlJ0s0SL90wkvyPCm4CE0kjLUo",
            "created": "2026-01-10T08:35:00Z",
            "company": {
                "display_name": "UnitedHealth Group",
                "__CLASS__": "Adzuna::API::Response::Company"
            },
            "salary_is_predicted": "0",
            "latitude": 12.95703,
            "longitude": 77.59837,
            "location": {
                "display_name": "Bangalore, Karnataka",
                "area": [
                    "India",
                    "Karnataka",
                    "Bangalore"
                ],
                "__CLASS__": "Adzuna::API::Response::Location"
            }
        },
        {
            "id": "5577273563",
            "description": "Optum is a global organization that delivers care, aided by technology to help millions of people live healthier lives. The work you do with our team will directly improve health outcomes by connecting people with the care, pharmacy benefits, data and resources they need to feel their best. Here, you will find a culture guided by inclusion, talented peers, comprehensive benefits and career development opportunities. Come make an impact on the communities we serve as you help us advance health o…",
            "title": "Senior Software Engineer II",
            "__CLASS__": "Adzuna::API::Response::Job",
            "category": {
                "label": "IT Jobs",
                "tag": "it-jobs",
                "__CLASS__": "Adzuna::API::Response::Category"
            },
            "redirect_url": "https://www.adzuna.in/land/ad/5577273563?se=uqmpVuPt8BGDxL9nTBzhZw&utm_medium=api&utm_source=d58ac19b&v=C1DC18DAF7137D3F2DA4130CD7033809356F1F63",
            "location": {
                "display_name": "Bangalore, Karnataka",
                "area": [
                    "India",
                    "Karnataka",
                    "Bangalore"
                ],
                "__CLASS__": "Adzuna::API::Response::Location"
            },
            "longitude": 77.59837,
            "latitude": 12.95703,
            "salary_is_predicted": "0",
            "company": {
                "__CLASS__": "Adzuna::API::Response::Company",
                "display_name": "UnitedHealth Group"
            },
            "created": "2026-01-10T08:35:00Z",
            "adref": "eyJhbGciOiJIUzI1NiJ9.eyJpIjoiNTU3NzI3MzU2MyIsInMiOiJ1cW1wVnVQdDhCR0R4TDluVEJ6aFp3In0.HMRIjhQcUkmRx9EmCRht61STjvHElR0oQQNqWuX6Y6c"
        },
        {
            "salary_is_predicted": "0",
            "company": {
                "display_name": "UnitedHealth Group",
                "__CLASS__": "Adzuna::API::Response::Company"
            },
            "latitude": 28.56579,
            "location": {
                "__CLASS__": "Adzuna::API::Response::Location",
                "area": [
                    "India",
                    "Uttar Pradesh",
                    "Ghaziabad",
                    "Noida"
                ],
                "display_name": "Noida, Ghaziabad"
            },
            "longitude": 77.3225,
            "adref": "eyJhbGciOiJIUzI1NiJ9.eyJpIjoiNTU3NzI3MzU2NSIsInMiOiJ1cW1wVnVQdDhCR0R4TDluVEJ6aFp3In0.WdSnaw0RykqOK9WBoaHPzvuXWtlRVkLRuBrjst7gItQ",
            "created": "2026-01-10T08:35:00Z",
            "category": {
                "__CLASS__": "Adzuna::API::Response::Category",
                "tag": "it-jobs",
                "label": "IT Jobs"
            },
            "__CLASS__": "Adzuna::API::Response::Job",
            "description": "Optum is a global organization that delivers care, aided by technology to help millions of people live healthier lives. The work you do with our team will directly improve health outcomes by connecting people with the care, pharmacy benefits, data and resources they need to feel their best. Here, you will find a culture guided by inclusion, talented peers, comprehensive benefits and career development opportunities. Come make an impact on the communities we serve as you help us advance health o…",
            "title": "Capability Analyst",
            "id": "5577273565",
            "redirect_url": "https://www.adzuna.in/land/ad/5577273565?se=uqmpVuPt8BGDxL9nTBzhZw&utm_medium=api&utm_source=d58ac19b&v=6E24C7BE7702493F70210434F616F80C5C4DC691"
        },
        {
            "redirect_url": "https://www.adzuna.in/land/ad/5577273546?se=uqmpVuPt8BGDxL9nTBzhZw&utm_medium=api&utm_source=d58ac19b&v=5AD6576F89C540C8831BE85D9FB0EEEC6CCFC97D",
            "description": "Description - External Optum is a global organization that delivers care, aided by technology to help millions of people live healthier lives. The work you do with our team will directly improve health outcomes by connecting people with the care, pharmacy benefits, data and resources they need to feel their best. Here, you will find a culture guided by inclusion, talented peers, comprehensive benefits and career development opportunities. Come make an impact on the communities we serve as you h…",
            "title": "Senior Capability Analyst",
            "category": {
                "label": "IT Jobs",
                "tag": "it-jobs",
                "__CLASS__": "Adzuna::API::Response::Category"
            },
            "__CLASS__": "Adzuna::API::Response::Job",
            "id": "5577273546",
            "adref": "eyJhbGciOiJIUzI1NiJ9.eyJzIjoidXFtcFZ1UHQ4QkdEeEw5blRCemhadyIsImkiOiI1NTc3MjczNTQ2In0.9fNQRgyrXOGJkqf5Y9DDzpnf_ch7zDHFZFUs_4qh1Fs",
            "created": "2026-01-10T08:34:59Z",
            "salary_is_predicted": "0",
            "company": {
                "display_name": "UnitedHealth Group",
                "__CLASS__": "Adzuna::API::Response::Company"
            },
            "location": {
                "display_name": "Noida, Ghaziabad",
                "area": [
                    "India",
                    "Uttar Pradesh",
                    "Ghaziabad",
                    "Noida"
                ],
                "__CLASS__": "Adzuna::API::Response::Location"
            },
            "longitude": 77.3225,
            "latitude": 28.56579
        },
        {
            "adref": "eyJhbGciOiJIUzI1NiJ9.eyJzIjoidXFtcFZ1UHQ4QkdEeEw5blRCemhadyIsImkiOiI1NTc3MjczNTYwIn0.yJZVn_NRLb7hvMW5hzqMeXRPoIqxlZBu12Amm70-CtE",
            "created": "2026-01-10T08:34:59Z",
            "salary_is_predicted": "0",
            "company": {
                "__CLASS__": "Adzuna::API::Response::Company",
                "display_name": "UnitedHealth Group"
            },
            "latitude": 12.95703,
            "location": {
                "__CLASS__": "Adzuna::API::Response::Location",
                "area": [
                    "India",
                    "Karnataka",
                    "Bangalore"
                ],
                "display_name": "Bangalore, Karnataka"
            },
            "longitude": 77.59837,
            "redirect_url": "https://www.adzuna.in/land/ad/5577273560?se=uqmpVuPt8BGDxL9nTBzhZw&utm_medium=api&utm_source=d58ac19b&v=B0CC856E4DE830C18056319F2C337AA6A430BED9",
            "__CLASS__": "Adzuna::API::Response::Job",
            "category": {
                "tag": "it-jobs",
                "label": "IT Jobs",
                "__CLASS__": "Adzuna::API::Response::Category"
            },
            "title": "Senior Full Stack Engineer",
            "description": "Optum is a global organization that delivers care, aided by technology to help millions of people live healthier lives. The work you do with our team will directly improve health outcomes by connecting people with the care, pharmacy benefits, data and resources they need to feel their best. Here, you will find a culture guided by inclusion, talented peers, comprehensive benefits and career development opportunities. Come make an impact on the communities we serve as you help us advance health o…",
            "id": "5577273560"
        },
        {
            "adref": "eyJhbGciOiJIUzI1NiJ9.eyJpIjoiNTU3NzI3MzU1OCIsInMiOiJ1cW1wVnVQdDhCR0R4TDluVEJ6aFp3In0.E_x4iZ-UIgH7B5xkOcr2Y0J-KkI0PBRUtOphgpuFDjc",
            "created": "2026-01-10T08:34:59Z",
            "company": {
                "__CLASS__": "Adzuna::API::Response::Company",
                "display_name": "UnitedHealth Group"
            },
            "salary_is_predicted": "0",
            "latitude": 12.95703,
            "location": {
                "area": [
                    "India",
                    "Karnataka",
                    "Bangalore"
                ],
                "display_name": "Bangalore, Karnataka",
                "__CLASS__": "Adzuna::API::Response::Location"
            },
            "longitude": 77.59837,
            "redirect_url": "https://www.adzuna.in/land/ad/5577273558?se=uqmpVuPt8BGDxL9nTBzhZw&utm_medium=api&utm_source=d58ac19b&v=DAA4B2E802036F7E539EEEDB287879BD784866BA",
            "__CLASS__": "Adzuna::API::Response::Job",
            "category": {
                "label": "IT Jobs",
                "tag": "it-jobs",
                "__CLASS__": "Adzuna::API::Response::Category"
            },
            "title": "Senior Manager Software Engineering",
            "description": "Optum is a global organization that delivers care, aided by technology to help millions of people live healthier lives. The work you do with our team will directly improve health outcomes by connecting people with the care, pharmacy benefits, data and resources they need to feel their best. Here, you will find a culture guided by inclusion, talented peers, comprehensive benefits and career development opportunities. Come make an impact on the communities we serve as you help us advance health o…",
            "id": "5577273558"
        },
        {
            "salary_is_predicted": "0",
            "company": {
                "__CLASS__": "Adzuna::API::Response::Company",
                "display_name": "UnitedHealth Group"
            },
            "latitude": 12.95703,
            "longitude": 77.59837,
            "location": {
                "__CLASS__": "Adzuna::API::Response::Location",
                "area": [
                    "India",
                    "Karnataka",
                    "Bangalore"
                ],
                "display_name": "Bangalore, Karnataka"
            },
            "adref": "eyJhbGciOiJIUzI1NiJ9.eyJpIjoiNTU3NzI3MzUzOSIsInMiOiJ1cW1wVnVQdDhCR0R4TDluVEJ6aFp3In0.b-1Db-jWjiZYt_w410Z1lulp0oE9mUuki3sg44LHGY4",
            "created": "2026-01-10T08:34:59Z",
            "category": {
                "__CLASS__": "Adzuna::API::Response::Category",
                "label": "IT Jobs",
                "tag": "it-jobs"
            },
            "__CLASS__": "Adzuna::API::Response::Job",
            "description": "Optum is a global organization that delivers care, aided by technology to help millions of people live healthier lives. The work you do with our team will directly improve health outcomes by connecting people with the care, pharmacy benefits, data and resources they need to feel their best. Here, you will find a culture guided by inclusion, talented peers, comprehensive benefits and career development opportunities. Come make an impact on the communities we serve as you help us advance health o…",
            "title": "Senior Software Engineering Lead - Python, Cloud, Gen AI",
            "id": "5577273539",
            "redirect_url": "https://www.adzuna.in/land/ad/5577273539?se=uqmpVuPt8BGDxL9nTBzhZw&utm_medium=api&utm_source=d58ac19b&v=5337E378E10E12B69EF92B3F955DC2C475B0B57B"
        },
        {
            "latitude": 12.95703,
            "location": {
                "area": [
                    "India",
                    "Karnataka",
                    "Bangalore"
                ],
                "display_name": "Bangalore, Karnataka",
                "__CLASS__": "Adzuna::API::Response::Location"
            },
            "longitude": 77.59837,
            "company": {
                "display_name": "UnitedHealth Group",
                "__CLASS__": "Adzuna::API::Response::Company"
            },
            "salary_is_predicted": "0",
            "created": "2026-01-10T08:34:59Z",
            "adref": "eyJhbGciOiJIUzI1NiJ9.eyJzIjoidXFtcFZ1UHQ4QkdEeEw5blRCemhadyIsImkiOiI1NTc3MjczNTM4In0.jqxKV1U7gssh_aYVlDDqNWPC088hiRw-1erDl84baG4",
            "id": "5577273538",
            "__CLASS__": "Adzuna::API::Response::Job",
            "category": {
                "tag": "it-jobs",
                "label": "IT Jobs",
                "__CLASS__": "Adzuna::API::Response::Category"
            },
            "title": "Senior Software Engineer I - Python, Cloud, Gen AI",
            "description": "Optum is a global organization that delivers care, aided by technology to help millions of people live healthier lives. The work you do with our team will directly improve health outcomes by connecting people with the care, pharmacy benefits, data and resources they need to feel their best. Here, you will find a culture guided by inclusion, talented peers, comprehensive benefits and career development opportunities. Come make an impact on the communities we serve as you help us advance health o…",
            "redirect_url": "https://www.adzuna.in/land/ad/5577273538?se=uqmpVuPt8BGDxL9nTBzhZw&utm_medium=api&utm_source=d58ac19b&v=38A2F5328E4A99FC5D531BBCCDF9E92B49178D3B"
        },
        {
            "adref": "eyJhbGciOiJIUzI1NiJ9.eyJzIjoidXFtcFZ1UHQ4QkdEeEw5blRCemhadyIsImkiOiI1NTc3MjczNTQzIn0.O9XAppR5eLrNKqwiueANAKqQyV1Y2h_f4bZF5bRjMtk",
            "created": "2026-01-10T08:34:59Z",
            "salary_is_predicted": "0",
            "company": {
                "display_name": "UnitedHealth Group",
                "__CLASS__": "Adzuna::API::Response::Company"
            },
            "latitude": 17.40275,
            "location": {
                "display_name": "Hyderabad, Telangana",
                "area": [
                    "India",
                    "Telangana",
                    "Hyderabad"
                ],
                "__CLASS__": "Adzuna::API::Response::Location"
            },
            "longitude": 78.50806,
            "redirect_url": "https://www.adzuna.in/land/ad/5577273543?se=uqmpVuPt8BGDxL9nTBzhZw&utm_medium=api&utm_source=d58ac19b&v=DF99E40031A8B9FCA5419777187870DCA2BAE9A4",
            "__CLASS__": "Adzuna::API::Response::Job",
            "category": {
                "label": "IT Jobs",
                "tag": "it-jobs",
                "__CLASS__": "Adzuna::API::Response::Category"
            },
            "title": "Senior Manager Software Engineering",
            "description": "Optum is a global organization that delivers care, aided by technology to help millions of people live healthier lives. The work you do with our team will directly improve health outcomes by connecting people with the care, pharmacy benefits, data and resources they need to feel their best. Here, you will find a culture guided by inclusion, talented peers, comprehensive benefits and career development opportunities. Come make an impact on the communities we serve as you help us advance health o…",
            "id": "5577273543"
        }
    ],
    "count": 6844
}