{
    "mean": 1502259.02,
    "results": [
        {
            "title": "Web Engineering Manager",
            "description": "Job Title: Web Engineering Manager (Sitecore, React, Node.js) Experience: 7 to 10 Years Location: Remote Employment Type: Full-time About the Role We are looking for a Engineering Manager to lead a mid-sized, high-performing team of backend, frontend, and QA engineers. The ideal candidate has strong experience in modern web technologies, Sitecore CMS, and building large-scale distributed web platforms. This role requires a balance of technical leadership, people management, and the ability to d…",
            "company": {
                "__CLASS__": "Adzuna::API::Response::Company",
                "display_name": "Closeloop Technologies Pvt. Ltd"
            },
            "id": "5546316933",
            "created": "2025-12-18T02:42:42Z",
            "contract_time": "full_time",
            "adref": "eyJhbGciOiJIUzI1NiJ9.eyJzIjoiU2xKclhGamk4QkdqSmFieFd0MGVEUSIsImkiOiI1NTQ2MzE2OTMzIn0.63adMPBkPOzN1wuHVdouJnw3s17IOtxFdVsu6AdfKnE",
            "redirect_url": "https://www.adzuna.in/land/ad/5546316933?se=SlJrXFji8BGjJabxWt0eDQ&utm_medium=api&utm_source=d58ac19b&v=3BBE87042DA1D001D9ED2DC14573B14FCD1B012E",
            "category": {
                "label": "IT Jobs",
                "__CLASS__": "Adzuna::API::Response::Category",
                "tag": "it-jobs"
            },
            "salary_is_predicted": "0",
            "__CLASS__": "Adzuna::API::Response::Job",
            "location": {
                "__CLASS__": "Adzuna::API::Response::Location",
                "area": [
                    "India"
                ],
                "display_name": "India"
            }
        },
        {
            "__CLASS__": "Adzuna::API::Response::Job",
            "location": {
                "area": [
                    "India",
                    "Telangana",
                    "Hyderabad"
                ],
                "display_name": "Hyderabad, Telangana",
                "__CLASS__": "Adzuna::API::Response::Location"
            },
            "latitude": 17.40275,
            "redirect_url": "https://www.adzuna.in/land/ad/5529806327?se=SlJrXFji8BGjJabxWt0eDQ&utm_medium=api&utm_source=d58ac19b&v=AB18262443ED25E154A3C1F791EC6957F7A4BFC2",
            "category": {
                "tag": "engineering-jobs",
                "__CLASS__": "Adzuna::API::Response::Category",
                "label": "Engineering Jobs"
            },
            "salary_is_predicted": "0",
            "longitude": 78.50806,
            "company": {
                "__CLASS__": "Adzuna::API::Response::Company",
                "display_name": "Endowus"
            },
            "description": "The Opportunity: Build the future of Wealth In a fintech world obsessed with gamification and speculative betting, Endowus stands apart. We aren't here to build another trading app; we are building the financial infrastructure to help people achieve long-term life goals - retirement, education, and financial freedom. Headquartered in Singapore, we are the largest independent digital wealth platform in Asia . However, we are not a one-trick robo-advisor. We are a full-suite wealth platform spann…",
            "id": "5529806327",
            "adref": "eyJhbGciOiJIUzI1NiJ9.eyJpIjoiNTUyOTgwNjMyNyIsInMiOiJTbEpyWEZqaThCR2pKYWJ4V3QwZURRIn0.w9-GUc1iE87dbivrV-d6-vs9sMz-FimkxX8mdi8k-C0",
            "created": "2025-12-06T01:27:54Z",
            "title": "Web Engineering (React / TypeScript)"
        },
        {
            "title": "Web & Product Engineer",
            "company": {
                "__CLASS__": "Adzuna::API::Response::Company",
                "display_name": "Kapable"
            },
            "longitude": 77.224601,
            "description": "About Kapable Kapable is a leadership transformation platform helping CXOs, founders, and senior professionals from top global companies become better leaders through our “Thinkable, Speakable, Workable” programs. We are not just building programs, we are building a full learning ecosystem . Every touchpoint from our marketing pages to the learner dashboard is powered by thoughtful engineering. If you are someone who enjoys building, automating, and solving real problems with clean code, this r…",
            "id": "5519967700",
            "adref": "eyJhbGciOiJIUzI1NiJ9.eyJzIjoiU2xKclhGamk4QkdqSmFieFd0MGVEUSIsImkiOiI1NTE5OTY3NzAwIn0.42V8L2R5c6E8CyLgXx4NQvQtLKvqnIK_wWTcX1LKVcA",
            "created": "2025-11-30T09:47:37Z",
            "redirect_url": "https://www.adzuna.in/land/ad/5519967700?se=SlJrXFji8BGjJabxWt0eDQ&utm_medium=api&utm_source=d58ac19b&v=54A41F84CB090C3484B6F08111E7F578BCA1DC19",
            "category": {
                "__CLASS__": "Adzuna::API::Response::Category",
                "tag": "it-jobs",
                "label": "IT Jobs"
            },
            "salary_is_predicted": "0",
            "__CLASS__": "Adzuna::API::Response::Job",
            "location": {
                "display_name": "Delhi, India",
                "area": [
                    "India",
                    "Delhi"
                ],
                "__CLASS__": "Adzuna::API::Response::Location"
            },
            "latitude": 28.62523
        },
        {
            "title": "Web Platform Engineer",
            "contract_time": "full_time",
            "adref": "eyJhbGciOiJIUzI1NiJ9.eyJzIjoiU2xKclhGamk4QkdqSmFieFd0MGVEUSIsImkiOiI1NTQ2MzE1OTQyIn0.tkjRp-gbrqUruQzKszxTXzeGdKtupy1ToJ7Afmq0e4U",
            "created": "2025-12-18T02:40:02Z",
            "description": "Who We Are White Rabbit Group is a company that partners with world class agencies for web and mobile app development and design, letting our customers focus on what they do best, while we focus on building. We have a broad spectrum of technologies that we work on including PHP, React, Node, Strapi, Shopify, WordPress, and fully native and hybrid mobile apps, to name a few. We have almost 100 full time employees spanned across the US, Colombia and India and we work closely together to bring our…",
            "company": {
                "display_name": "White Rabbit Group",
                "__CLASS__": "Adzuna::API::Response::Company"
            },
            "longitude": 76.24637,
            "id": "5546315942",
            "salary_is_predicted": "0",
            "redirect_url": "https://www.adzuna.in/land/ad/5546315942?se=SlJrXFji8BGjJabxWt0eDQ&utm_medium=api&utm_source=d58ac19b&v=4F4543B6BCEAB2F5AE3285A94EA7B09EC1C89A95",
            "category": {
                "__CLASS__": "Adzuna::API::Response::Category",
                "tag": "it-jobs",
                "label": "IT Jobs"
            },
            "latitude": 9.98011,
            "__CLASS__": "Adzuna::API::Response::Job",
            "location": {
                "area": [
                    "India",
                    "Kerala",
                    "Ernakulam",
                    "Kochi"
                ],
                "display_name": "Kochi, Ernakulam",
                "__CLASS__": "Adzuna::API::Response::Location"
            }
        },
        {
            "created": "2025-11-24T07:14:11Z",
            "adref": "eyJhbGciOiJIUzI1NiJ9.eyJpIjoiNTUxMDkzNjk4MyIsInMiOiJTbEpyWEZqaThCR2pKYWJ4V3QwZURRIn0.xiArFivbMcrwNPLWKS8RzeqUTNNN_wibgrjwNpHTy-8",
            "description": "Responsibilities: · Collaborate with cross-functional teams to understand project requirements · Come up with Test Plan and write Test Cases for Mobile Applications/Web Applications · Execute the Test Cases Manually and provide sign Offs · Define test automation strategies. · Develop and maintain end-to-end test suites using Detox to validate web applications. · Create and execute automated test scripts for regression, functional, and performance testing. · Identify and report defects, track is…",
            "company": {
                "__CLASS__": "Adzuna::API::Response::Company",
                "display_name": "BayOne Solutions"
            },
            "id": "5510936983",
            "title": "Mobile/Web QA Engineer",
            "__CLASS__": "Adzuna::API::Response::Job",
            "location": {
                "__CLASS__": "Adzuna::API::Response::Location",
                "area": [
                    "India"
                ],
                "display_name": "India"
            },
            "salary_is_predicted": "0",
            "category": {
                "tag": "it-jobs",
                "__CLASS__": "Adzuna::API::Response::Category",
                "label": "IT Jobs"
            },
            "redirect_url": "https://www.adzuna.in/land/ad/5510936983?se=SlJrXFji8BGjJabxWt0eDQ&utm_medium=api&utm_source=d58ac19b&v=C53BB535E2E1D8CEA156A45F5D2E98B6C81FBB42"
        },
        {
            "title": "Mobile and Web QA Engineer (BANGALORE)",
            "id": "5434982897",
            "description": "o Please apply if you are willing to work at our Bangalore office o Be part of our team operating in stealth mode before our product launch in October o An attractive compensation based on professional background and skills. o Accommodation and meals will be taken care during your stay. o Join us now and be part of our exciting 4-day trip to Thailand (or another destination) following our first launch! Note: o Before applying, please read the job description thoroughly and ensure it aligns with…",
            "company": {
                "__CLASS__": "Adzuna::API::Response::Company",
                "display_name": "Zuchiz"
            },
            "adref": "eyJhbGciOiJIUzI1NiJ9.eyJzIjoiU2xKclhGamk4QkdqSmFieFd0MGVEUSIsImkiOiI1NDM0OTgyODk3In0.yLTMVuhX9wX_ImE0yw1xAp0wLUBr2ixCZeTgbb42gv0",
            "created": "2025-10-07T09:47:35Z",
            "redirect_url": "https://www.adzuna.in/land/ad/5434982897?se=SlJrXFji8BGjJabxWt0eDQ&utm_medium=api&utm_source=d58ac19b&v=C6600BADA01FBAC83F8A597EF321122A9025BCCA",
            "category": {
                "label": "IT Jobs",
                "tag": "it-jobs",
                "__CLASS__": "Adzuna::API::Response::Category"
            },
            "salary_is_predicted": "0",
            "location": {
                "__CLASS__": "Adzuna::API::Response::Location",
                "area": [
                    "India",
                    "Karnataka",
                    "Bangalore"
                ],
                "display_name": "Bangalore, Karnataka"
            },
            "__CLASS__": "Adzuna::API::Response::Job"
        },
        {
            "id": "5518770978",
            "company": {
                "display_name": "Pocket FM",
                "__CLASS__": "Adzuna::API::Response::Company"
            },
            "description": "Software Engineer-Web Location: Bengaluru Experience: 1-3 years About Pocket FM Pocket FM, founded in 2018, is India’s leading audio storytelling platform, transforming the way millions consume stories. Offering high-quality serialized content across genres such as Romance, Drama, Thriller, Fantasy, Sci-Fi, and Mythology in eight languages, Pocket FM has built a strong global presence with over 200 million listeners worldwide. With users spending an average of 120 minutes daily on the platform,…",
            "adref": "eyJhbGciOiJIUzI1NiJ9.eyJpIjoiNTUxODc3MDk3OCIsInMiOiJTbEpyWEZqaThCR2pKYWJ4V3QwZURRIn0.CNCYS1ZSpTfIefraM8TgVp7K5Vxd5jsnnId8RFp9aP0",
            "created": "2025-11-29T10:10:43Z",
            "title": "Software Engineer - Web",
            "location": {
                "display_name": "India",
                "area": [
                    "India"
                ],
                "__CLASS__": "Adzuna::API::Response::Location"
            },
            "__CLASS__": "Adzuna::API::Response::Job",
            "redirect_url": "https://www.adzuna.in/land/ad/5518770978?se=SlJrXFji8BGjJabxWt0eDQ&utm_medium=api&utm_source=d58ac19b&v=2215B60BFD3129C88DF4E3F23440A7137FE4972D",
            "category": {
                "tag": "engineering-jobs",
                "__CLASS__": "Adzuna::API::Response::Category",
                "label": "Engineering Jobs"
            },
            "salary_is_predicted": "0"
        },
        {
            "company": {
                "__CLASS__": "Adzuna::API::Response::Company",
                "display_name": "Pocket FM"
            },
            "description": "Senior Software Engineer-Web Location: Bengaluru Experience: 3–6 years About Pocket FM Pocket FM, founded in 2018, is India’s leading audio storytelling platform, transforming the way millions consume stories. Offering high-quality serialized content across genres such as Romance, Drama, Thriller, Fantasy, Sci-Fi, and Mythology in eight languages, Pocket FM has built a strong global presence with over 200 million listeners worldwide. With users spending an average of 120 minutes daily on the pl…",
            "id": "5525210772",
            "created": "2025-12-03T09:04:10Z",
            "adref": "eyJhbGciOiJIUzI1NiJ9.eyJzIjoiU2xKclhGamk4QkdqSmFieFd0MGVEUSIsImkiOiI1NTI1MjEwNzcyIn0.ky878OKh9Dga4826_iNVwt6ghbUQGl3ivLw2Clv2v-k",
            "title": "Senior Software Engineer-Web",
            "__CLASS__": "Adzuna::API::Response::Job",
            "location": {
                "display_name": "India",
                "area": [
                    "India"
                ],
                "__CLASS__": "Adzuna::API::Response::Location"
            },
            "category": {
                "label": "Engineering Jobs",
                "__CLASS__": "Adzuna::API::Response::Category",
                "tag": "engineering-jobs"
            },
            "redirect_url": "https://www.adzuna.in/land/ad/5525210772?se=SlJrXFji8BGjJabxWt0eDQ&utm_medium=api&utm_source=d58ac19b&v=094810510A75D5F6902D2E0987ACA1B9ED10405C",
            "salary_is_predicted": "0"
        },
        {
            "id": "5464582573",
            "company": {
                "display_name": "Alternative Path",
                "__CLASS__": "Adzuna::API::Response::Company"
            },
            "description": "Alternative Path is seeking skilled software developers to collaborate on client projects with an asset management firm. In this role, you will collaborate with individuals across various company departments to shape and innovate new products and features for our platform, enhancing existing ones. You will have a large degree of independence and trust, but you won't be isolated; the support of the Engineering team leads, the Product team leads, and every other technology team member is behind y…",
            "created": "2025-10-26T02:17:35Z",
            "adref": "eyJhbGciOiJIUzI1NiJ9.eyJzIjoiU2xKclhGamk4QkdqSmFieFd0MGVEUSIsImkiOiI1NDY0NTgyNTczIn0.QTWO-Ut4-I6nl6Tid5Ya_SLJFS0ijIYzxbspZ09PUww",
            "title": "Data Engineer - Web Scraping",
            "location": {
                "__CLASS__": "Adzuna::API::Response::Location",
                "area": [
                    "India"
                ],
                "display_name": "India"
            },
            "__CLASS__": "Adzuna::API::Response::Job",
            "redirect_url": "https://www.adzuna.in/land/ad/5464582573?se=SlJrXFji8BGjJabxWt0eDQ&utm_medium=api&utm_source=d58ac19b&v=ADE3E0481E5DE0E916267E750FF0D15082145449",
            "category": {
                "__CLASS__": "Adzuna::API::Response::Category",
                "tag": "it-jobs",
                "label": "IT Jobs"
            },
            "salary_is_predicted": "0"
        },
        {
            "salary_is_predicted": "0",
            "redirect_url": "https://www.adzuna.in/land/ad/5537383471?se=SlJrXFji8BGjJabxWt0eDQ&utm_medium=api&utm_source=d58ac19b&v=7D5BCFFC953E5D6D1339A83B1B78D63928B7852C",
            "category": {
                "__CLASS__": "Adzuna::API::Response::Category",
                "tag": "it-jobs",
                "label": "IT Jobs"
            },
            "location": {
                "__CLASS__": "Adzuna::API::Response::Location",
                "display_name": "Bangalore, Karnataka",
                "area": [
                    "India",
                    "Karnataka",
                    "Bangalore"
                ]
            },
            "__CLASS__": "Adzuna::API::Response::Job",
            "title": "Sr. Software Engineer - Web Platform (Frontend Engineering), Digital Business (Location: Bangalore)",
            "created": "2025-12-11T09:26:43Z",
            "adref": "eyJhbGciOiJIUzI1NiJ9.eyJpIjoiNTUzNzM4MzQ3MSIsInMiOiJTbEpyWEZqaThCR2pKYWJ4V3QwZURRIn0.-AwsIAa7po_rlUP2BiihzvHxFVcbYb0vJUt7nW3Q40A",
            "id": "5537383471",
            "description": "Sr. Software Engineer - Web Platform, Digital Business Bengaluru (1005), Technology Overview We are seeking a talented and passionate React Developer to join our team and play a key role in the development and maintenance of internal backend tools and dashboards. You will be responsible for building and maintaining high-quality, user-friendly interfaces that empower our engineering and operations teams. Location - Bangalore Education - B.E./B.Tech, MCA or Equivalent Computer Degree Essential Ex…",
            "company": {
                "display_name": "Sony Pictures Networks India",
                "__CLASS__": "Adzuna::API::Response::Company"
            }
        },
        {
            "location": {
                "display_name": "India",
                "area": [
                    "India"
                ],
                "__CLASS__": "Adzuna::API::Response::Location"
            },
            "__CLASS__": "Adzuna::API::Response::Job",
            "salary_is_predicted": "0",
            "category": {
                "tag": "it-jobs",
                "__CLASS__": "Adzuna::API::Response::Category",
                "label": "IT Jobs"
            },
            "redirect_url": "https://www.adzuna.in/land/ad/5556102770?se=SlJrXFji8BGjJabxWt0eDQ&utm_medium=api&utm_source=d58ac19b&v=8FD65333022D757BAFB28EBEA389BD3E04EC7579",
            "created": "2025-12-26T08:36:15Z",
            "adref": "eyJhbGciOiJIUzI1NiJ9.eyJzIjoiU2xKclhGamk4QkdqSmFieFd0MGVEUSIsImkiOiI1NTU2MTAyNzcwIn0.-SMdfByRoAlKMcmR370pNTPp6JVhhJv__5hLgwcDlR8",
            "id": "5556102770",
            "description": "About Job We empower the people who build the world. Taiyō.AI is the world's first infrastructure intelligence platform that helps some of the world’s large infrastructure companies proactively manage opportunities and threats in a dynamic world. We are building the largest universal and industry standard database of opportunities (tenders, projects, news) and threats (economy, climate, geopolitics, finance, logistics, etc) for real assets. Taiyō.AI has been instrumental in shaping how infrastr…",
            "company": {
                "display_name": "Taiyō.AI",
                "__CLASS__": "Adzuna::API::Response::Company"
            },
            "title": "Python Developer (Web Scraping Data Engineer)"
        },
        {
            "redirect_url": "https://www.adzuna.in/land/ad/5553092448?se=SlJrXFji8BGjJabxWt0eDQ&utm_medium=api&utm_source=d58ac19b&v=0685ED44A4B3EE28C247CAB1E3250DE611C15442",
            "category": {
                "label": "Engineering Jobs",
                "__CLASS__": "Adzuna::API::Response::Category",
                "tag": "engineering-jobs"
            },
            "salary_is_predicted": "0",
            "location": {
                "area": [
                    "India"
                ],
                "display_name": "India",
                "__CLASS__": "Adzuna::API::Response::Location"
            },
            "__CLASS__": "Adzuna::API::Response::Job",
            "title": "Data Engineer - Mobile & Web Scrapping",
            "id": "5553092448",
            "company": {
                "__CLASS__": "Adzuna::API::Response::Company",
                "display_name": "Gala Intelligence"
            },
            "description": "We're looking for an entrepreneurial, passionate, and driven Data Engineer to join Startup Gala Intelligence backed by Navneet Tech Venture situated in Ahmedabad . As we're building our technology platform from scratch, you'll have the unique opportunity to shape our technology vision, architecture, and engineering culture right from the ground up. You’ll directly contribute to foundational development and establish best practices, while eventually building and contributing to our engineering t…",
            "created": "2025-12-24T00:01:08Z",
            "adref": "eyJhbGciOiJIUzI1NiJ9.eyJpIjoiNTU1MzA5MjQ0OCIsInMiOiJTbEpyWEZqaThCR2pKYWJ4V3QwZURRIn0.-LDaVjyGFZeBi9PFXpWItcY7D559Ad9kWSHI9CiKucE"
        },
        {
            "adref": "eyJhbGciOiJIUzI1NiJ9.eyJpIjoiNTU0MzI0OTE1MSIsInMiOiJTbEpyWEZqaThCR2pKYWJ4V3QwZURRIn0.OQfvqtKU_kPS65xqVYbpeoOrZhQF9qbHAAh7eYKFlfQ",
            "contract_time": "full_time",
            "created": "2025-12-16T00:15:21Z",
            "company": {
                "display_name": "BatchData",
                "__CLASS__": "Adzuna::API::Response::Company"
            },
            "description": "Position Overview Job Title: Web Engineer Work Hours: Full-time (8 hours/day, Mon-Fri) Location: Remote Job Summary As a Web Engineer at BatchData, you will work as a Node.js/TypeScript developer within our Data Engineering team. As part of the organization’s data ecosystem, you will use cutting-edge technologies in the big data and analytics space and contribute to projects using modern tools to support data-driven systems. Your role includes developing high-performance, highly available REST …",
            "id": "5543249151",
            "title": "Web Engineer",
            "__CLASS__": "Adzuna::API::Response::Job",
            "location": {
                "area": [
                    "India",
                    "Karnataka",
                    "Bangalore"
                ],
                "display_name": "Bangalore, Karnataka",
                "__CLASS__": "Adzuna::API::Response::Location"
            },
            "salary_is_predicted": "0",
            "category": {
                "label": "IT Jobs",
                "tag": "it-jobs",
                "__CLASS__": "Adzuna::API::Response::Category"
            },
            "redirect_url": "https://www.adzuna.in/details/5543249151?utm_medium=api&utm_source=d58ac19b"
        },
        {
            "created": "2025-11-27T09:43:20Z",
            "adref": "eyJhbGciOiJIUzI1NiJ9.eyJpIjoiNTUxNTY5MTEzOCIsInMiOiJTbEpyWEZqaThCR2pKYWJ4V3QwZURRIn0.s6UY4evnPQwjkmWa9AjjR7XSW2XEdJuJIQb5ZpZ5Fb8",
            "id": "5515691138",
            "description": "You will work closely with Client Success and support them by providing Tier-2 client support for software technical issues and work with Engineering department to debug and resolve the issues. RESPONSIBILITIES: Provide technical support to internal and external users including customer service teams as well as clients and partners Communication and coordination of feedback and inputs to the development team, mostly based in India Assist QA lead with QA activities Troubleshooting technical issu…",
            "company": {
                "__CLASS__": "Adzuna::API::Response::Company",
                "display_name": "Textellent, Inc."
            },
            "title": "Technical Support Engineer for a Web/Mobile application for US Company",
            "location": {
                "__CLASS__": "Adzuna::API::Response::Location",
                "area": [
                    "India"
                ],
                "display_name": "India"
            },
            "__CLASS__": "Adzuna::API::Response::Job",
            "salary_is_predicted": "0",
            "redirect_url": "https://www.adzuna.in/land/ad/5515691138?se=SlJrXFji8BGjJabxWt0eDQ&utm_medium=api&utm_source=d58ac19b&v=763AA070392340D967E17C2892F4580982B36D7E",
            "category": {
                "label": "IT Jobs",
                "__CLASS__": "Adzuna::API::Response::Category",
                "tag": "it-jobs"
            }
        },
        {
            "title": "Web Engineer II",
            "contract_time": "full_time",
            "created": "2025-12-13T00:18:25Z",
            "adref": "eyJhbGciOiJIUzI1NiJ9.eyJpIjoiNTUzOTg0ODIzNCIsInMiOiJTbEpyWEZqaThCR2pKYWJ4V3QwZURRIn0.N0F1LpuU-XiItwiSxHkK-6dPs08yM1UxUkHdErccXGQ",
            "id": "5539848234",
            "company": {
                "display_name": "Arrow",
                "__CLASS__": "Adzuna::API::Response::Company"
            },
            "description": "Position: Web Engineer II Job Description: Candidate with 4 to 7 years of strong hands-on design/development background in Microsoft technologies and application integrations. Able to translate requirements into design/code with unit testing/ bug fixing / tuning Understanding basics of APIs for testing and troubleshooting Hands-on development experience with Power Platform Ability to interpret data related to energy usage, carbon emissions, employee commute, waste management, or supply chain ES…",
            "salary_is_predicted": "0",
            "redirect_url": "https://www.adzuna.in/details/5539848234?utm_medium=api&utm_source=d58ac19b",
            "category": {
                "label": "IT Jobs",
                "__CLASS__": "Adzuna::API::Response::Category",
                "tag": "it-jobs"
            },
            "location": {
                "__CLASS__": "Adzuna::API::Response::Location",
                "area": [
                    "India"
                ],
                "display_name": "India"
            },
            "__CLASS__": "Adzuna::API::Response::Job"
        },
        {
            "salary_is_predicted": "0",
            "category": {
                "tag": "it-jobs",
                "__CLASS__": "Adzuna::API::Response::Category",
                "label": "IT Jobs"
            },
            "salary_max": 3000000,
            "latitude": 12.91448,
            "__CLASS__": "Adzuna::API::Response::Job",
            "location": {
                "__CLASS__": "Adzuna::API::Response::Location",
                "display_name": "Mangalore, Dakshin Kannada",
                "area": [
                    "India",
                    "Karnataka",
                    "Dakshin Kannada",
                    "Mangalore"
                ]
            },
            "salary_min": 100000,
            "title": "Principal Web Engineer",
            "contract_time": "full_time",
            "description": "ABOUT THE ROLE: As a Principal Web Engineer, we are on looking for a box thinker who can help us solve real-time complex problems. You need to help us in making our product more robust and scalable since we are majorly working on B2B segment. You should be a Seasoned Web Developer who has the capabilities to build Web Apps from Scratch & work with minimal supervision. ROLES AND RESPONSIBILITIES • Understand product requirements and features and translate them into technical requirements (collab…",
            "longitude": 75.18597,
            "redirect_url": "https://www.adzuna.in/details/3290772327?utm_medium=api&utm_source=d58ac19b",
            "adref": "eyJhbGciOiJIUzI1NiJ9.eyJzIjoiU2xKclhGamk4QkdqSmFieFd0MGVEUSIsImkiOiIzMjkwNzcyMzI3In0.rclV_QIN-56HNgZqNMxz-m1FUw0LYqMRuf59dVGS_ic",
            "created": "2022-07-05T06:41:24Z",
            "company": {
                "__CLASS__": "Adzuna::API::Response::Company",
                "display_name": "Zyvka Global Services"
            },
            "id": "3290772327"
        },
        {
            "redirect_url": "https://www.adzuna.in/details/5537505615?utm_medium=api&utm_source=d58ac19b",
            "category": {
                "tag": "it-jobs",
                "__CLASS__": "Adzuna::API::Response::Category",
                "label": "IT Jobs"
            },
            "salary_is_predicted": "0",
            "__CLASS__": "Adzuna::API::Response::Job",
            "location": {
                "area": [
                    "India",
                    "Karnataka",
                    "Bangalore"
                ],
                "display_name": "Bangalore, Karnataka",
                "__CLASS__": "Adzuna::API::Response::Location"
            },
            "latitude": 12.95703,
            "title": "Web Engineer II",
            "company": {
                "display_name": "Arrow Electronics",
                "__CLASS__": "Adzuna::API::Response::Company"
            },
            "description": "Position: Web Engineer II Job Description: Candidate with 4 to 7 years of strong hands-on design/development background in Microsoft technologies and application integrations. Able to translate requirements into design/code with unit testing/ bug fixing / tuning Understanding basics of APIs for testing and troubleshooting Hands-on development experience with Power Platform Ability to interpret data related to energy usage, carbon emissions, employee commute, waste management, or supply chain ES…",
            "longitude": 77.59837,
            "id": "5537505615",
            "created": "2025-12-11T11:38:21Z",
            "adref": "eyJhbGciOiJIUzI1NiJ9.eyJzIjoiU2xKclhGamk4QkdqSmFieFd0MGVEUSIsImkiOiI1NTM3NTA1NjE1In0.RhWpYwXhFsEI7D4W8Sdq_T5pKh72jgrLf9qXJgy3RU0"
        },
        {
            "adref": "eyJhbGciOiJIUzI1NiJ9.eyJzIjoiU2xKclhGamk4QkdqSmFieFd0MGVEUSIsImkiOiI1NTQ2MzE1ODA2In0.HzAO2zOg525Km5tjvjC-N609M0uOmqmCBu0xHjOB5Kw",
            "created": "2025-12-18T02:39:54Z",
            "id": "5546315806",
            "description": "Company Vision StockGro is India’s leading stock market education platform with a community of over 2.5 crore market enthusiasts. StockGro equips users with trading and investing knowledge to succeed in the stock market. Whether user is a beginner or a seasoned trader, he can learn strategies from top investment managers, practice with platform currency, and study portfolios of experts & peers. By combining experiential learning with guidance from SEBl-registered experts, StockGro has become th…",
            "company": {
                "display_name": "StockGro",
                "__CLASS__": "Adzuna::API::Response::Company"
            },
            "title": "Frontend Engineer",
            "location": {
                "display_name": "Bangalore, Karnataka",
                "area": [
                    "India",
                    "Karnataka",
                    "Bangalore"
                ],
                "__CLASS__": "Adzuna::API::Response::Location"
            },
            "__CLASS__": "Adzuna::API::Response::Job",
            "salary_is_predicted": "0",
            "category": {
                "__CLASS__": "Adzuna::API::Response::Category",
                "tag": "it-jobs",
                "label": "IT Jobs"
            },
            "redirect_url": "https://www.adzuna.in/land/ad/5546315806?se=SlJrXFji8BGjJabxWt0eDQ&utm_medium=api&utm_source=d58ac19b&v=FF15057CEB74683913C4EF8F95B1FE59684C4963"
        },
        {
            "salary_is_predicted": "0",
            "category": {
                "__CLASS__": "Adzuna::API::Response::Category",
                "tag": "it-jobs",
                "label": "IT Jobs"
            },
            "redirect_url": "https://www.adzuna.in/details/5501832539?utm_medium=api&utm_source=d58ac19b",
            "location": {
                "area": [
                    "India",
                    "Karnataka",
                    "Bangalore"
                ],
                "display_name": "Bangalore, Karnataka",
                "__CLASS__": "Adzuna::API::Response::Location"
            },
            "__CLASS__": "Adzuna::API::Response::Job",
            "title": "Sr Web Engineer (WEB-02)",
            "adref": "eyJhbGciOiJIUzI1NiJ9.eyJpIjoiNTUwMTgzMjUzOSIsInMiOiJTbEpyWEZqaThCR2pKYWJ4V3QwZURRIn0.0M3oOWXgMZfZE51LKnZkfhBtLykO-VMLbJP5oaHHe_w",
            "contract_time": "full_time",
            "created": "2025-11-18T22:16:42Z",
            "id": "5501832539",
            "description": "We are looking for developers well verse in Web technologies using Java (and/or) Python, HTML5, Javascript and has a practical understanding of how to build websites. You will be working on responsive and user friendly web/mobile sites. Responsibilities: - Develop 3-tier web applications, you will be required to contribute on both HTML/JS and on Backend technologies. - Develop charts/graphs for reports on internal dashboards. - Deliver high quality, legible and well tested code. - Develop user …",
            "company": {
                "display_name": "Carzonrent India / Carzonrent Labs",
                "__CLASS__": "Adzuna::API::Response::Company"
            }
        },
        {
            "salary_is_predicted": "0",
            "category": {
                "label": "IT Jobs",
                "__CLASS__": "Adzuna::API::Response::Category",
                "tag": "it-jobs"
            },
            "salary_max": 4000000,
            "redirect_url": "https://www.adzuna.in/details/5540348345?utm_medium=api&utm_source=d58ac19b",
            "contract_type": "permanent",
            "__CLASS__": "Adzuna::API::Response::Job",
            "location": {
                "__CLASS__": "Adzuna::API::Response::Location",
                "display_name": "Bangalore, Karnataka",
                "area": [
                    "India",
                    "Karnataka",
                    "Bangalore"
                ]
            },
            "salary_min": 2000000,
            "title": "Technical Lead – Web Engineering",
            "adref": "eyJhbGciOiJIUzI1NiJ9.eyJzIjoiU2xKclhGamk4QkdqSmFieFd0MGVEUSIsImkiOiI1NTQwMzQ4MzQ1In0.m8-ck1MKT-U69UiPosHVzyxhAdu-W8LnSs3xvxW8iYk",
            "contract_time": "full_time",
            "created": "2025-12-13T03:28:31Z",
            "company": {
                "display_name": "Kuku FM",
                "__CLASS__": "Adzuna::API::Response::Company"
            },
            "description": "We are seeking a highly skilled Technical Lead – Web to own and scale the KukuFM web platform to millions of users. This role requires deep expertise in frontend architecture, modern web technologies, and building highly performant, secure, and reliable user experiences—including our web player (audio/video) and web-based payments flow. As a Technical Lead, you will drive architectural decisions, ensure engineering quality, and build a world-class, end-to-end web experience across browsers and …",
            "id": "5540348345"
        },
        {
            "salary_min": 500000,
            "title": "Web Engineering Lead (ReactjsTypescript)",
            "contract_time": "full_time",
            "longitude": 73.84735,
            "description": "Job description T Location: Pune  Mode: Hybrid  Employment Type: Permanent Overview: Are you a JavaScript and TypeScript enthusiast passionate about building user-friendly and visually appealing web applications? If you have 5 years of React experience (preferably in SaaS), we’d love to have you join Azodha, a digital healthcare startup! As a React Software Development Engineer, you will play a key role in developing and maintaining our web-based healthcare platform. You'll be responsible for b…",
            "salary_is_predicted": "0",
            "contract_type": "permanent",
            "category": {
                "label": "IT Jobs",
                "tag": "it-jobs",
                "__CLASS__": "Adzuna::API::Response::Category"
            },
            "salary_max": 2200000,
            "latitude": 18.5062,
            "location": {
                "display_name": "Pune, Maharashtra",
                "area": [
                    "India",
                    "Maharashtra",
                    "Pune"
                ],
                "__CLASS__": "Adzuna::API::Response::Location"
            },
            "__CLASS__": "Adzuna::API::Response::Job",
            "created": "2025-11-25T07:14:05Z",
            "adref": "eyJhbGciOiJIUzI1NiJ9.eyJpIjoiNTUxMTk3OTE2MCIsInMiOiJTbEpyWEZqaThCR2pKYWJ4V3QwZURRIn0.4G2cYGH0AWlkwCCU8-0meYSI28c2-btGjGhwYKnu0FY",
            "id": "5511979160",
            "company": {
                "display_name": "Azodha",
                "__CLASS__": "Adzuna::API::Response::Company"
            },
            "redirect_url": "https://www.adzuna.in/details/5511979160?utm_medium=api&utm_source=d58ac19b"
        },
        {
            "title": "QA Engineer – Manual & Automation (Web  Mobile | 4–6 Years Experience)",
            "id": "5542702050",
            "company": {
                "display_name": "Textellent, Inc.",
                "__CLASS__": "Adzuna::API::Response::Company"
            },
            "description": "QA Engineer – Manual & Automation (Web  Mobile | 4–6 Years Experience) About Textellent, Inc. Textellent, Inc. is a leading SMS marketing platform that integrates with CRM systems to automate and personalize marketing, sales, and customer service campaigns. Our platform also offers self-service appointment scheduling with pre- and post-appointment drip campaigns. We are expanding our QA team to ensure our web and mobile SaaS applications deliver a seamless, high-quality user experience across d…",
            "created": "2025-12-15T08:40:45Z",
            "adref": "eyJhbGciOiJIUzI1NiJ9.eyJzIjoiU2xKclhGamk4QkdqSmFieFd0MGVEUSIsImkiOiI1NTQyNzAyMDUwIn0.GnYeQA0BEVj46tvFxHiaMkZr_TmZupP9fAtakHCR8v8",
            "category": {
                "label": "IT Jobs",
                "tag": "it-jobs",
                "__CLASS__": "Adzuna::API::Response::Category"
            },
            "redirect_url": "https://www.adzuna.in/land/ad/5542702050?se=SlJrXFji8BGjJabxWt0eDQ&utm_medium=api&utm_source=d58ac19b&v=85E533D5BA5C42C42415F3139D72968FC94F8172",
            "salary_is_predicted": "0",
            "location": {
                "__CLASS__": "Adzuna::API::Response::Location",
                "display_name": "India",
                "area": [
                    "India"
                ]
            },
            "__CLASS__": "Adzuna::API::Response::Job"
        },
        {
            "title": "Senior Program Manager",
            "id": "5546599325",
            "company": {
                "__CLASS__": "Adzuna::API::Response::Company",
                "display_name": "Inspektlabs"
            },
            "description": "Location : Delhi Experience : 3–8 years Function : Product execution, client workflows, delivery coordination About the Role We are hiring a Senior Program Manager to act as a cross-functional execution owner across product development, senior client workflow discussions, and delivery coordination. This role exists to bridge gaps between founders, engineers, operations, and customers — ensuring clarity, prioritization, and follow-through. This is not a pure PM role and not a sales role. It is a…",
            "created": "2025-12-18T08:44:53Z",
            "adref": "eyJhbGciOiJIUzI1NiJ9.eyJpIjoiNTU0NjU5OTMyNSIsInMiOiJTbEpyWEZqaThCR2pKYWJ4V3QwZURRIn0.MoGBMMGfXpt8Rq-CFEzUcANGunKBipE7JIqsXAyT1YM",
            "redirect_url": "https://www.adzuna.in/land/ad/5546599325?se=SlJrXFji8BGjJabxWt0eDQ&utm_medium=api&utm_source=d58ac19b&v=189627F44D4B052DC7BDAAA884DAA18F85DED080",
            "category": {
                "tag": "it-jobs",
                "__CLASS__": "Adzuna::API::Response::Category",
                "label": "IT Jobs"
            },
            "salary_is_predicted": "0",
            "location": {
                "display_name": "India",
                "area": [
                    "India"
                ],
                "__CLASS__": "Adzuna::API::Response::Location"
            },
            "__CLASS__": "Adzuna::API::Response::Job"
        },
        {
            "location": {
                "__CLASS__": "Adzuna::API::Response::Location",
                "display_name": "Bangalore, Karnataka",
                "area": [
                    "India",
                    "Karnataka",
                    "Bangalore"
                ]
            },
            "__CLASS__": "Adzuna::API::Response::Job",
            "redirect_url": "https://www.adzuna.in/land/ad/5515705685?se=SlJrXFji8BGjJabxWt0eDQ&utm_medium=api&utm_source=d58ac19b&v=CBC535F2596847D49A85CEAD23BA35F4E196A36F",
            "category": {
                "label": "IT Jobs",
                "__CLASS__": "Adzuna::API::Response::Category",
                "tag": "it-jobs"
            },
            "salary_is_predicted": "0",
            "id": "5515705685",
            "company": {
                "display_name": "Primenumbers",
                "__CLASS__": "Adzuna::API::Response::Company"
            },
            "description": "About Us : Palladium by Primenumbers Technologies : A leading tech platform trusted by over 500 mid to large-sized enterprise companies. Purpose : Delivers advanced insights and cutting-edge technology to drive revenue growth and profitability. Core Features : Enhances search capabilities and streamlines critical operations in business processes. Our Team : Founded by two IIT engineers with extensive tech expertise. Vision : Revolutionising the tendering process for businesses with innovative t…",
            "created": "2025-11-27T09:51:38Z",
            "adref": "eyJhbGciOiJIUzI1NiJ9.eyJpIjoiNTUxNTcwNTY4NSIsInMiOiJTbEpyWEZqaThCR2pKYWJ4V3QwZURRIn0.QUKDidFifE3U5JAodcbD6r5Qpo_Z1GCgohmL5TnTr8g",
            "title": "Software Development Engineer"
        },
        {
            "salary_max": 3000000,
            "category": {
                "label": "IT Jobs",
                "__CLASS__": "Adzuna::API::Response::Category",
                "tag": "it-jobs"
            },
            "redirect_url": "https://www.adzuna.in/details/4514375962?utm_medium=api&utm_source=d58ac19b",
            "salary_is_predicted": "0",
            "__CLASS__": "Adzuna::API::Response::Job",
            "location": {
                "area": [
                    "India",
                    "Karnataka",
                    "Bangalore"
                ],
                "display_name": "Bangalore, Karnataka",
                "__CLASS__": "Adzuna::API::Response::Location"
            },
            "salary_min": 1200000,
            "title": "Software Engineer (Web/UI Engineer)",
            "description": "Software Engineer (Web/UI Engineer) Please apply only if you satisfy work experience requirements Our Vision , we are building a first-of-its-kind, lifestyle health product for Women in India. We believe that the future of health and fitness is digital, and women will drive the digital fitness revolution in India. Existing digital health and fitness products are highly transactional and we see a huge opportunity to build a truly aspirational product that will inspire and empower millions of wom…",
            "company": {
                "display_name": "Qrata",
                "__CLASS__": "Adzuna::API::Response::Company"
            },
            "id": "4514375962",
            "contract_time": "full_time",
            "adref": "eyJhbGciOiJIUzI1NiJ9.eyJzIjoiU2xKclhGamk4QkdqSmFieFd0MGVEUSIsImkiOiI0NTE0Mzc1OTYyIn0.Lsr00hVy-zD8nN9WxNxlmZw6VD3HV2bJm-1_3qr3ioc",
            "created": "2024-01-07T15:07:40Z"
        },
        {
            "title": "Senior Software Engineer I [T500-21316]",
            "adref": "eyJhbGciOiJIUzI1NiJ9.eyJpIjoiNTU0ODEzOTkwMSIsInMiOiJTbEpyWEZqaThCR2pKYWJ4V3QwZURRIn0.Q5iXGA4e9UD8pvmDZvuO0-SjTRdJ-jZ1-A1IV_skjoY",
            "created": "2025-12-19T09:00:27Z",
            "id": "5548139901",
            "longitude": 78.50806,
            "company": {
                "__CLASS__": "Adzuna::API::Response::Company",
                "display_name": "Marriott Tech Accelerator"
            },
            "description": "About Us: Marriott International Inc. , headquartered in Bethesda, Maryland, USA, was founded in May 1927 by J. Willard Marriott and Alice S. Marriott with a modest nine-seat A&W root beer stand. Guided by the family's leadership and core principles, Marriott International today has grown into a global hospitality giant, operating approximately 9,000 properties and over 30 leading brands in more than 140 countries and territories. From such humble beginnings to becoming the world’s largest hote…",
            "salary_is_predicted": "0",
            "category": {
                "__CLASS__": "Adzuna::API::Response::Category",
                "tag": "it-jobs",
                "label": "IT Jobs"
            },
            "redirect_url": "https://www.adzuna.in/land/ad/5548139901?se=SlJrXFji8BGjJabxWt0eDQ&utm_medium=api&utm_source=d58ac19b&v=4A23E6D54B9DCB729BCBF78AF3EE865A91B10F00",
            "latitude": 17.40275,
            "location": {
                "__CLASS__": "Adzuna::API::Response::Location",
                "area": [
                    "India",
                    "Telangana",
                    "Hyderabad"
                ],
                "display_name": "Hyderabad, Telangana"
            },
            "__CLASS__": "Adzuna::API::Response::Job"
        },
        {
            "category": {
                "tag": "it-jobs",
                "__CLASS__": "Adzuna::API::Response::Category",
                "label": "IT Jobs"
            },
            "salary_max": 4000000,
            "redirect_url": "https://www.adzuna.in/details/5128160979?utm_medium=api&utm_source=d58ac19b",
            "salary_is_predicted": "0",
            "__CLASS__": "Adzuna::API::Response::Job",
            "location": {
                "area": [
                    "India",
                    "Karnataka",
                    "Bangalore"
                ],
                "display_name": "Bangalore, Karnataka",
                "__CLASS__": "Adzuna::API::Response::Location"
            },
            "title": "Senior Fullstack Web Engineer (PHP, Javascript / Typescript",
            "salary_min": 2500000,
            "company": {
                "display_name": "Talent Pro",
                "__CLASS__": "Adzuna::API::Response::Company"
            },
            "description": "Role & Responsibilities Contributes to the technical vision for an engineering team, aligning with company-wide strategies and goals. Contributes to the design and development of robust, scalable, and user-friendly web applications. Create innovative solutions using the latest technologies and tools for front end development and backend development. Collaborate with product managers, designers, and engineers to define product direction and to deliver complex applications. Conduct thorough code …",
            "id": "5128160979",
            "contract_time": "full_time",
            "adref": "eyJhbGciOiJIUzI1NiJ9.eyJpIjoiNTEyODE2MDk3OSIsInMiOiJTbEpyWEZqaThCR2pKYWJ4V3QwZURRIn0.3002ATPYVZ71MtiQfszfVxj_JnKwQiRV5PjFsRiaHoo",
            "created": "2025-04-04T04:37:21Z"
        },
        {
            "__CLASS__": "Adzuna::API::Response::Job",
            "location": {
                "area": [
                    "India"
                ],
                "display_name": "India",
                "__CLASS__": "Adzuna::API::Response::Location"
            },
            "category": {
                "label": "IT Jobs",
                "tag": "it-jobs",
                "__CLASS__": "Adzuna::API::Response::Category"
            },
            "redirect_url": "https://www.adzuna.in/details/3433222322?utm_medium=api&utm_source=d58ac19b",
            "salary_max": 500000,
            "salary_is_predicted": "0",
            "company": {
                "display_name": "Diginnovators Solution Pvt Ltd",
                "__CLASS__": "Adzuna::API::Response::Company"
            },
            "description": "PHP / Laravel developer is an IT professional specialized in developing web applications using Laravel Framework within PHP programming language. In order to attract PHP / Laravel developer that best matches your needs, it is very important to write a clear and precise PHP / Laravel developer job description. Responsibilities: Develop, record and maintain cutting edge web-based PHP applications on portal plus premium service platforms Build innovative, state-of-the-art applications and collabor…",
            "id": "3433222322",
            "adref": "eyJhbGciOiJIUzI1NiJ9.eyJpIjoiMzQzMzIyMjMyMiIsInMiOiJTbEpyWEZqaThCR2pKYWJ4V3QwZURRIn0.M7EvbbFyvqFquAveDnYeb06DoTmIYURo2U3_blifB2o",
            "contract_time": "full_time",
            "created": "2022-08-26T06:41:28Z",
            "salary_min": 150000,
            "title": "Backend â PHP/Laravel â Web Engineer"
        },
        {
            "contract_time": "full_time",
            "longitude": 80.24963,
            "description": "Role : Web Scraping Engineer Experience : 2 to 3 Years Job Location : Chennai About OJ Commerce: OJ Commerce (OJC), a rapidly expanding and profitable online retailer, is headquartered in Florida, USA, with a fully-functional office in Chennai, India. We deliver exceptional value to our customers by harnessing cutting-edge technology, fostering innovation, and establishing strategic brand partnerships to enable a seamless, enjoyable shopping experience featuring high-quality products at unbeata…",
            "title": "Web Scraping Engineer",
            "salary_min": 700000,
            "latitude": 13.06041,
            "__CLASS__": "Adzuna::API::Response::Job",
            "location": {
                "area": [
                    "India",
                    "Tamil Nadu",
                    "Chennai"
                ],
                "display_name": "Chennai, Tamil Nadu",
                "__CLASS__": "Adzuna::API::Response::Location"
            },
            "salary_is_predicted": "0",
            "category": {
                "label": "IT Jobs",
                "__CLASS__": "Adzuna::API::Response::Category",
                "tag": "it-jobs"
            },
            "salary_max": 1200000,
            "adref": "eyJhbGciOiJIUzI1NiJ9.eyJpIjoiNDU0MTgyODYzNSIsInMiOiJTbEpyWEZqaThCR2pKYWJ4V3QwZURRIn0.n4fpyW7Jf-AKaJlsfoalqLEWr6mVuSiJPWwTBDPzvuw",
            "created": "2024-01-24T15:35:19Z",
            "company": {
                "display_name": "OJCommerce",
                "__CLASS__": "Adzuna::API::Response::Company"
            },
            "id": "4541828635",
            "redirect_url": "https://www.adzuna.in/details/4541828635?utm_medium=api&utm_source=d58ac19b"
        },
        {
            "company": {
                "__CLASS__": "Adzuna::API::Response::Company",
                "display_name": "Google"
            },
            "description": "Web Solutions Engineer _corporate_fare_ Google _place_ Bengaluru, Karnataka, India Mid Experience driving progress, solving problems, and mentoring more junior team members; deeper expertise and applied knowledge within relevant area. Minimum qualifications:  Bachelor's degree in Computer Science, a similar technical field, or equivalent practical experience.  4 years of experience in software development.  Experience in programming with at least one of: Java, Python, GoLang, or TypeScript/Java…",
            "id": "5508593018",
            "adref": "eyJhbGciOiJIUzI1NiJ9.eyJpIjoiNTUwODU5MzAxOCIsInMiOiJTbEpyWEZqaThCR2pKYWJ4V3QwZURRIn0.QQClxYYDNIsMPsUAbGvgCKST56aqPnxaN9t0-hCjvJ4",
            "created": "2025-11-22T05:49:16Z",
            "title": "Web Solutions Engineer",
            "__CLASS__": "Adzuna::API::Response::Job",
            "location": {
                "__CLASS__": "Adzuna::API::Response::Location",
                "display_name": "Bangalore, Karnataka",
                "area": [
                    "India",
                    "Karnataka",
                    "Bangalore"
                ]
            },
            "redirect_url": "https://www.adzuna.in/details/5508593018?utm_medium=api&utm_source=d58ac19b",
            "category": {
                "tag": "it-jobs",
                "__CLASS__": "Adzuna::API::Response::Category",
                "label": "IT Jobs"
            },
            "salary_is_predicted": "0"
        },
        {
            "redirect_url": "https://www.adzuna.in/details/5510413604?utm_medium=api&utm_source=d58ac19b",
            "category": {
                "tag": "it-jobs",
                "__CLASS__": "Adzuna::API::Response::Category",
                "label": "IT Jobs"
            },
            "salary_is_predicted": "0",
            "__CLASS__": "Adzuna::API::Response::Job",
            "location": {
                "__CLASS__": "Adzuna::API::Response::Location",
                "area": [
                    "India",
                    "Karnataka",
                    "Bangalore"
                ],
                "display_name": "Bangalore, Karnataka"
            },
            "title": "Web Solutions Engineer",
            "description": "Minimum qualifications: Bachelor's degree in Computer Science, a similar technical field, or equivalent practical experience. 4 years of experience in software development. Experience in programming with at least one of: Java, Python, GoLang, or TypeScript/JavaScript. Preferred qualifications: Experience in using test frameworks, CRMs, and Billing systems, and with machine learning, data analysis, and data science. Experience with unit testing, agile project development, bug and change manageme…",
            "company": {
                "__CLASS__": "Adzuna::API::Response::Company",
                "display_name": "Google"
            },
            "id": "5510413604",
            "created": "2025-11-23T22:27:53Z",
            "adref": "eyJhbGciOiJIUzI1NiJ9.eyJzIjoiU2xKclhGamk4QkdqSmFieFd0MGVEUSIsImkiOiI1NTEwNDEzNjA0In0.TlxPgs4_bjEW-3_-_pgvAXfG2TCzAYf3c9fVzbM2BZ4"
        },
        {
            "id": "5341050941",
            "description": "SFO Technologies (http://www.sfotechnologies.net/) is a 25 year old organization with strong presence in communication (fiber optic devices, RF communication systems, STB…), health care (ultrasound scanners, x-ray equipments, nuclear medicine…), transportation (metro fare collection gates, automotive electronics…) and value added engineering services. We serve multiple tier-1 clients - GE, Toshiba, ALSTOM, DIEBOLD, HITACHI, THALES to name a few. Our vision is to be a globally respected leader i…",
            "company": {
                "__CLASS__": "Adzuna::API::Response::Company",
                "display_name": "SFO Technologies"
            },
            "contract_time": "full_time",
            "created": "2025-08-07T05:37:46Z",
            "adref": "eyJhbGciOiJIUzI1NiJ9.eyJzIjoiU2xKclhGamk4QkdqSmFieFd0MGVEUSIsImkiOiI1MzQxMDUwOTQxIn0.9obuNcX3Zs9Ikumf3-3kMw_i8Ms9zRaWt4Z0s3ffnAs",
            "title": "Web Application Engineers",
            "salary_min": 700000,
            "location": {
                "__CLASS__": "Adzuna::API::Response::Location",
                "area": [
                    "India",
                    "Karnataka",
                    "Bangalore"
                ],
                "display_name": "Bangalore, Karnataka"
            },
            "__CLASS__": "Adzuna::API::Response::Job",
            "redirect_url": "https://www.adzuna.in/details/5341050941?utm_medium=api&utm_source=d58ac19b",
            "category": {
                "__CLASS__": "Adzuna::API::Response::Category",
                "tag": "it-jobs",
                "label": "IT Jobs"
            },
            "salary_max": 1400000,
            "salary_is_predicted": "0"
        },
        {
            "redirect_url": "https://www.adzuna.in/details/1155088475?utm_medium=api&utm_source=d58ac19b",
            "id": 1155088475,
            "company": {
                "__CLASS__": "Adzuna::API::Response::Company",
                "display_name": "BlueOptima"
            },
            "adref": "eyJhbGciOiJIUzI1NiJ9.eyJpIjoxMTU1MDg4NDc1LCJzIjoiU2xKclhGamk4QkdqSmFieFd0MGVEUSJ9.Zqq_B6qXzczQ8Hlws4b-Yp4zNsYEWZhoBN_xt-MbQM8",
            "created": "2019-05-17T21:02:39Z",
            "location": {
                "__CLASS__": "Adzuna::API::Response::Location",
                "area": [
                    "India",
                    "Maharashtra",
                    "Navi Mumbai"
                ],
                "display_name": "Navi Mumbai, Maharashtra"
            },
            "__CLASS__": "Adzuna::API::Response::Job",
            "latitude": 19.02,
            "category": {
                "tag": "it-jobs",
                "__CLASS__": "Adzuna::API::Response::Category",
                "label": "IT Jobs"
            },
            "salary_max": 1500000,
            "salary_is_predicted": "0",
            "description": "\"Responsibilities Include Develop, test, implement and maintain application software Take part in software and architectural development activities Transform requirements into implementation details Debug application issues and helping support respond to client queries Participate in application development meetings Provide accurate estimates, clearly communicate status of tasks and identification of risks Commitment to accomplishing the task at hand and identify the fastest and most reliable w…",
            "longitude": 73.02,
            "contract_time": "full_time",
            "title": "Web Backend Engineer",
            "salary_min": 1200000
        },
        {
            "salary_is_predicted": "0",
            "redirect_url": "https://www.adzuna.in/details/4801526340?utm_medium=api&utm_source=d58ac19b",
            "category": {
                "label": "IT Jobs",
                "__CLASS__": "Adzuna::API::Response::Category",
                "tag": "it-jobs"
            },
            "location": {
                "__CLASS__": "Adzuna::API::Response::Location",
                "display_name": "India",
                "area": [
                    "India"
                ]
            },
            "__CLASS__": "Adzuna::API::Response::Job",
            "title": "Web Development Engineer",
            "adref": "eyJhbGciOiJIUzI1NiJ9.eyJzIjoiU2xKclhGamk4QkdqSmFieFd0MGVEUSIsImkiOiI0ODAxNTI2MzQwIn0.k85tca72lwbwWOGr9I4GHRkxTkN-Kvp_diS9ipqy5Bo",
            "created": "2024-07-31T03:13:04Z",
            "id": "4801526340",
            "company": {
                "display_name": "Nevales Networks .",
                "__CLASS__": "Adzuna::API::Response::Company"
            },
            "description": "We need candidates with Sophisticated Technology enthusiast with PHP Object Oriented development experience and MVC Design Projects. Job Description: Web application developers that are skilled in developing on Linux Mysql Apache and PHP platforms. The position exists to design, develop, test, maintain and support high performance, scalable, innovative web-based applications. Candidate must be energetic, self-motivated problem solver who works well in teams and must have ability to adapt to a r…"
        },
        {
            "contract_type": "permanent",
            "redirect_url": "https://www.adzuna.in/details/5545623610?utm_medium=api&utm_source=d58ac19b",
            "category": {
                "label": "IT Jobs",
                "tag": "it-jobs",
                "__CLASS__": "Adzuna::API::Response::Category"
            },
            "salary_is_predicted": "0",
            "location": {
                "__CLASS__": "Adzuna::API::Response::Location",
                "display_name": "Kolkata, West Bengal",
                "area": [
                    "India",
                    "West Bengal",
                    "Kolkata"
                ]
            },
            "__CLASS__": "Adzuna::API::Response::Job",
            "latitude": 22.57285,
            "title": "AVP, Web Engineer III - Apply Buy Digital (L10)",
            "id": "5545623610",
            "longitude": 88.34373,
            "company": {
                "__CLASS__": "Adzuna::API::Response::Company",
                "display_name": "Synchrony"
            },
            "description": "JOB_POSTING-3-76476-2 Job Description Role Title: AVP, Web Engineer III - Apply Buy Digital (L10) Company Overview Synchrony (NYSE: SYF) is a premier consumer financial services company delivering one of the industry’s most complete digitally enabled product suites. Our experience, expertise and scale encompass a broad spectrum of industries including digital, health and wellness, retail, telecommunications, home, auto, outdoors, pet and more. We have recently been ranked 2 among India’s Best C…",
            "contract_time": "full_time",
            "created": "2025-12-17T20:02:33Z",
            "adref": "eyJhbGciOiJIUzI1NiJ9.eyJpIjoiNTU0NTYyMzYxMCIsInMiOiJTbEpyWEZqaThCR2pKYWJ4V3QwZURRIn0.g44ky-nRqvZWnM_gtVLxEKwnmUgGNv66Hx7z6xBJld4"
        },
        {
            "title": "WAF Radware Engineer",
            "description": "Job Overview: We are looking for a skilled WAF (Web Application Firewall) Engineer with hands-on experience in Radware solutions. The ideal candidate will be responsible for deploying, configuring, managing, and optimizing Radware WAF to ensure the highest levels of application security and performance. Key Responsibilities: Deploy, configure, and maintain Radware Web Application Firewall solutions. Monitor, analyze, and fine-tune WAF policies to protect against OWASP Top 10 and emerging threat…",
            "company": {
                "__CLASS__": "Adzuna::API::Response::Company",
                "display_name": "Soffit Infrastructure Services  Ltd"
            },
            "longitude": 77.3225,
            "id": "5523455494",
            "created": "2025-12-02T08:56:23Z",
            "adref": "eyJhbGciOiJIUzI1NiJ9.eyJzIjoiU2xKclhGamk4QkdqSmFieFd0MGVEUSIsImkiOiI1NTIzNDU1NDk0In0.Y3qtOE9HJzmduDBELyzwUQ04JOvdEqy_lHOKBpKAYoA",
            "category": {
                "label": "IT Jobs",
                "tag": "it-jobs",
                "__CLASS__": "Adzuna::API::Response::Category"
            },
            "redirect_url": "https://www.adzuna.in/land/ad/5523455494?se=SlJrXFji8BGjJabxWt0eDQ&utm_medium=api&utm_source=d58ac19b&v=7D40A2D39C4A50F865F7007F2273339A6F239CC6",
            "salary_is_predicted": "0",
            "__CLASS__": "Adzuna::API::Response::Job",
            "location": {
                "area": [
                    "India",
                    "Uttar Pradesh",
                    "Ghaziabad",
                    "Noida"
                ],
                "display_name": "Noida, Ghaziabad",
                "__CLASS__": "Adzuna::API::Response::Location"
            },
            "latitude": 28.56579
        },
        {
            "location": {
                "__CLASS__": "Adzuna::API::Response::Location",
                "area": [
                    "India",
                    "Telangana",
                    "Hyderabad"
                ],
                "display_name": "Hyderabad, Telangana"
            },
            "__CLASS__": "Adzuna::API::Response::Job",
            "redirect_url": "https://www.adzuna.in/details/4801464452?utm_medium=api&utm_source=d58ac19b",
            "category": {
                "label": "IT Jobs",
                "tag": "it-jobs",
                "__CLASS__": "Adzuna::API::Response::Category"
            },
            "salary_is_predicted": "0",
            "id": "4801464452",
            "description": "A Web Applications Engineer is a talented coder who builds systems that improve players’ experience to efficiently communicate and enjoy in highly energy packed game rooms. Utilizing open source technology and frameworks our goal is to focus on creating innovative and game changing ideas. Sample applications may include online-game engines, web-based enterprise applications, distributed database tools, ticketing and customer relationship management systems, intelligent data retrieval tools. Exp…",
            "company": {
                "__CLASS__": "Adzuna::API::Response::Company",
                "display_name": "fortuity"
            },
            "adref": "eyJhbGciOiJIUzI1NiJ9.eyJzIjoiU2xKclhGamk4QkdqSmFieFd0MGVEUSIsImkiOiI0ODAxNDY0NDUyIn0.MWyGomGx0iMmAdsDPSuBy8bAgF5zDQX-A1UZfR53jJM",
            "created": "2024-07-31T03:07:43Z",
            "title": "Web Applications Engineer - PHP"
        },
        {
            "salary_is_predicted": "0",
            "redirect_url": "https://www.adzuna.in/details/5529332195?utm_medium=api&utm_source=d58ac19b",
            "category": {
                "__CLASS__": "Adzuna::API::Response::Category",
                "tag": "it-jobs",
                "label": "IT Jobs"
            },
            "__CLASS__": "Adzuna::API::Response::Job",
            "location": {
                "__CLASS__": "Adzuna::API::Response::Location",
                "area": [
                    "India",
                    "Karnataka",
                    "Bangalore"
                ],
                "display_name": "Bangalore, Karnataka"
            },
            "title": "Junior Web Application Engineers",
            "created": "2025-12-05T22:39:59Z",
            "contract_time": "full_time",
            "adref": "eyJhbGciOiJIUzI1NiJ9.eyJzIjoiU2xKclhGamk4QkdqSmFieFd0MGVEUSIsImkiOiI1NTI5MzMyMTk1In0.T1E6xfLB0mlSrd2nhEnt1fjVu0I-dkecweE1cHj7FWo",
            "company": {
                "__CLASS__": "Adzuna::API::Response::Company",
                "display_name": "Weekday"
            },
            "description": "This role is for one of our clients Industry: Internet Publishing Seniority level: Entry level Min Experience: 0 years Location: Bangalore JobType: full-time ₹4,00,000 - ₹6,00,000 a year We are looking for enthusiastic and driven Junior Web Application Engineers to join our Solutions team. In this role, you will contribute to building and enhancing real-world technology solutions that enable large-scale asset and inventory tracking for enterprise clients. You’ll work closely with engineering an…",
            "id": "5529332195"
        },
        {
            "location": {
                "area": [
                    "India",
                    "Karnataka",
                    "Bangalore"
                ],
                "display_name": "Bangalore, Karnataka",
                "__CLASS__": "Adzuna::API::Response::Location"
            },
            "__CLASS__": "Adzuna::API::Response::Job",
            "redirect_url": "https://www.adzuna.in/details/1155088482?utm_medium=api&utm_source=d58ac19b",
            "category": {
                "tag": "it-jobs",
                "__CLASS__": "Adzuna::API::Response::Category",
                "label": "IT Jobs"
            },
            "salary_max": 1200000,
            "salary_is_predicted": "0",
            "id": 1155088482,
            "description": "Whom are we looking for? Our groundbreaking technology, requires highly skilled and talented Web Backend Developers to understand the depth of the problem and device a solution for it.We are seeking a Software Engineer, with a depth of experience in developing Web Applications enabled using REST APIs backed by a data warehouse solution, to join our growing company and be a part of our success story. We are looking for individual with great attention to detail, who is genuine, confident, committ…",
            "company": {
                "display_name": "BlueOptima",
                "__CLASS__": "Adzuna::API::Response::Company"
            },
            "adref": "eyJhbGciOiJIUzI1NiJ9.eyJpIjoxMTU1MDg4NDgyLCJzIjoiU2xKclhGamk4QkdqSmFieFd0MGVEUSJ9.sQLtZ6lxhqa0LAFwdw9ERj8zMjbBuVX4ugZZxxOfiE8",
            "contract_time": "full_time",
            "created": "2019-05-17T21:02:39Z",
            "title": "Associate Web Backend Engineer",
            "salary_min": 700000
        },
        {
            "created": "2019-05-17T21:02:40Z",
            "contract_time": "full_time",
            "adref": "eyJhbGciOiJIUzI1NiJ9.eyJpIjoxMTU1MDg4NjA2LCJzIjoiU2xKclhGamk4QkdqSmFieFd0MGVEUSJ9.TnQmjdYYnm9diJwwP_ZowhCARn9ROPjePad9vX_Udr4",
            "id": 1155088606,
            "description": "Who are we? BlueOptima provides industry-leading objective metrics in software development using our proprietary Coding Effort Analytics. We enable large organisations to deliver better software, faster and at lower cost. Founded in 2006, BlueOptima is a profitable, high-growth independent software company. Our unique technology was initially devised in seminal research carried out at Cambridge University. We are headquartered in London with offices in New York, Bangalore, Gurgaon and Guadalaja…",
            "company": {
                "__CLASS__": "Adzuna::API::Response::Company",
                "display_name": "BlueOptima"
            },
            "salary_min": 3000000,
            "title": "Principal Web Backend Engineer",
            "location": {
                "__CLASS__": "Adzuna::API::Response::Location",
                "display_name": "Bangalore, Karnataka",
                "area": [
                    "India",
                    "Karnataka",
                    "Bangalore"
                ]
            },
            "__CLASS__": "Adzuna::API::Response::Job",
            "salary_is_predicted": "0",
            "redirect_url": "https://www.adzuna.in/details/1155088606?utm_medium=api&utm_source=d58ac19b",
            "category": {
                "tag": "it-jobs",
                "__CLASS__": "Adzuna::API::Response::Category",
                "label": "IT Jobs"
            },
            "salary_max": 5000000
        },
        {
            "title": "Sr. Web Enablement Engineer",
            "company": {
                "display_name": "Addepar",
                "__CLASS__": "Adzuna::API::Response::Company"
            },
            "description": "Who We Are Addepar is a global technology and data company that helps investment professionals provide the most informed, precise guidance for their clients. Hundreds of thousands of users have entrusted Addepar to empower smarter investment decisions and better advice over the last decade. With client presence in more than 50 countries, Addepar's platform aggregates portfolio, market and client data for over $8 trillion in assets. Addepar's open platform integrates with more than 100 software,…",
            "longitude": 73.84735,
            "id": "5488119620",
            "adref": "eyJhbGciOiJIUzI1NiJ9.eyJpIjoiNTQ4ODExOTYyMCIsInMiOiJTbEpyWEZqaThCR2pKYWJ4V3QwZURRIn0.AXBTvU6qqa8vRZfeY6obn6TvaidE3MaUt4WOv81WsmI",
            "created": "2025-11-09T16:08:11Z",
            "category": {
                "__CLASS__": "Adzuna::API::Response::Category",
                "tag": "it-jobs",
                "label": "IT Jobs"
            },
            "redirect_url": "https://www.adzuna.in/details/5488119620?utm_medium=api&utm_source=d58ac19b",
            "salary_is_predicted": "0",
            "__CLASS__": "Adzuna::API::Response::Job",
            "location": {
                "__CLASS__": "Adzuna::API::Response::Location",
                "area": [
                    "India",
                    "Maharashtra",
                    "Pune"
                ],
                "display_name": "Pune, Maharashtra"
            },
            "latitude": 18.5062
        },
        {
            "redirect_url": "https://www.adzuna.in/details/5488127254?utm_medium=api&utm_source=d58ac19b",
            "category": {
                "tag": "it-jobs",
                "__CLASS__": "Adzuna::API::Response::Category",
                "label": "IT Jobs"
            },
            "salary_is_predicted": "0",
            "__CLASS__": "Adzuna::API::Response::Job",
            "location": {
                "__CLASS__": "Adzuna::API::Response::Location",
                "display_name": "Pune, Maharashtra",
                "area": [
                    "India",
                    "Maharashtra",
                    "Pune"
                ]
            },
            "latitude": 18.5062,
            "title": "Staff Web Enablement Engineer",
            "company": {
                "display_name": "Addepar",
                "__CLASS__": "Adzuna::API::Response::Company"
            },
            "description": "Who We Are Addepar is a global technology and data company that helps investment professionals provide the most informed, precise guidance for their clients. Hundreds of thousands of users have entrusted Addepar to empower smarter investment decisions and better advice over the last decade. With client presence in more than 50 countries, Addepar's platform aggregates portfolio, market and client data for over $8 trillion in assets. Addepar's open platform integrates with more than 100 software,…",
            "longitude": 73.84735,
            "id": "5488127254",
            "created": "2025-11-09T16:16:32Z",
            "contract_time": "full_time",
            "adref": "eyJhbGciOiJIUzI1NiJ9.eyJpIjoiNTQ4ODEyNzI1NCIsInMiOiJTbEpyWEZqaThCR2pKYWJ4V3QwZURRIn0.n8Hp4oKmLsfGEJxHvAaOsXKx8tGcFUU-kSCJ5SPwqmQ"
        },
        {
            "salary_is_predicted": "0",
            "redirect_url": "https://www.adzuna.in/details/5509378147?utm_medium=api&utm_source=d58ac19b",
            "category": {
                "label": "IT Jobs",
                "tag": "it-jobs",
                "__CLASS__": "Adzuna::API::Response::Category"
            },
            "latitude": 17.40275,
            "location": {
                "__CLASS__": "Adzuna::API::Response::Location",
                "display_name": "Hyderabad, Telangana",
                "area": [
                    "India",
                    "Telangana",
                    "Hyderabad"
                ]
            },
            "__CLASS__": "Adzuna::API::Response::Job",
            "title": "Sr. Web Application Engineer",
            "contract_time": "full_time",
            "adref": "eyJhbGciOiJIUzI1NiJ9.eyJzIjoiU2xKclhGamk4QkdqSmFieFd0MGVEUSIsImkiOiI1NTA5Mzc4MTQ3In0.2Y1CFVoY4bkp1lNcPV7cNfmv3fVK-xGO0cg-kjJnWig",
            "created": "2025-11-22T22:43:53Z",
            "id": "5509378147",
            "description": "Web Developer: • Strong in JavaScript, CSS3 and HTML5 & Bootstrap framework. • Responsive Web Design • Experience in Front end framework – AngularJS (Mandatory) • Knowledge in AJAX, JSON • SQL Programming • Vaadin Framework ( Optional )",
            "company": {
                "display_name": "Rankworld",
                "__CLASS__": "Adzuna::API::Response::Company"
            },
            "longitude": 78.50806
        },
        {
            "title": "Application Security Engineer",
            "id": "5549497986",
            "description": "Role: Application Security Engineer Skills Required: • At lease 3 years of Application Security Experience • Experience with SAST, SCA, DAST • Experience with Python, C#, or Javascript • Experience security testing for Web Applications Application Security Engineer (Analyst?) - Job Description As the Application Security Engineer (Analyst) at the Information Security team, you will support security analysis and security support activities into software solutions. You will have the opportunity t…",
            "company": {
                "display_name": "KPG99 INC",
                "__CLASS__": "Adzuna::API::Response::Company"
            },
            "adref": "eyJhbGciOiJIUzI1NiJ9.eyJzIjoiU2xKclhGamk4QkdqSmFieFd0MGVEUSIsImkiOiI1NTQ5NDk3OTg2In0.pzrP_e6-avkdWcia3wb_GkpOAENjSmzL593oK01bGWs",
            "created": "2025-12-20T09:02:04Z",
            "category": {
                "__CLASS__": "Adzuna::API::Response::Category",
                "tag": "it-jobs",
                "label": "IT Jobs"
            },
            "redirect_url": "https://www.adzuna.in/land/ad/5549497986?se=SlJrXFji8BGjJabxWt0eDQ&utm_medium=api&utm_source=d58ac19b&v=CA28789AEEFA512DBA71A5BE9614DE0D4884985F",
            "salary_is_predicted": "0",
            "location": {
                "area": [
                    "India"
                ],
                "display_name": "India",
                "__CLASS__": "Adzuna::API::Response::Location"
            },
            "__CLASS__": "Adzuna::API::Response::Job"
        },
        {
            "id": "5546316433",
            "description": "Role: Software Engineer(mobile & web) Location: Kochi infopark Experience: 6 -10 years Mandatory skills: React, Reactnative, C++/ PHP Budget: max 22lpa Qualification: BTech/MCA Your tasks: As Senior Software Engineer with a strong background in React, React Native , C++, and PHP you will be part of a Product Engineering team. We are looking for engineers with a passion for programming and a product mindset. Responsibilities include: Enhance and maintain a mobile app. Enhance and maintain a web …",
            "company": {
                "__CLASS__": "Adzuna::API::Response::Company",
                "display_name": "Velodata Global Pvt Ltd"
            },
            "longitude": 76.24637,
            "created": "2025-12-18T02:41:24Z",
            "adref": "eyJhbGciOiJIUzI1NiJ9.eyJpIjoiNTU0NjMxNjQzMyIsInMiOiJTbEpyWEZqaThCR2pKYWJ4V3QwZURRIn0.NsPUwf1_54HPEJTg2eKZ86ml77qD-vrxukFEUudqDVs",
            "title": "Software Engineer",
            "location": {
                "area": [
                    "India",
                    "Kerala",
                    "Ernakulam",
                    "Kochi"
                ],
                "display_name": "Kochi, Ernakulam",
                "__CLASS__": "Adzuna::API::Response::Location"
            },
            "__CLASS__": "Adzuna::API::Response::Job",
            "latitude": 9.98011,
            "redirect_url": "https://www.adzuna.in/land/ad/5546316433?se=SlJrXFji8BGjJabxWt0eDQ&utm_medium=api&utm_source=d58ac19b&v=5BBB3F5EE67CACD82A2841922DFAFF56CCE2ADEE",
            "category": {
                "label": "IT Jobs",
                "tag": "it-jobs",
                "__CLASS__": "Adzuna::API::Response::Category"
            },
            "salary_is_predicted": "0"
        },
        {
            "adref": "eyJhbGciOiJIUzI1NiJ9.eyJpIjoiNTU0OTQ5Nzg5MSIsInMiOiJTbEpyWEZqaThCR2pKYWJ4V3QwZURRIn0.XEnEwJ0dUBisgZkbv7FL_AGDY8u-yXMJNPJZLSdplSc",
            "created": "2025-12-20T09:01:59Z",
            "id": "5549497891",
            "description": "Role : Application Security Engineer (SAST, SCA, DAST) Location : Remote (India) Skills Required: • At least 3 years of Application Security Experience • Experience with SAST, SCA, DAST • Experience with Python, C#, or Javascript • Experience security testing for Web Applications Application Security Engineer (Analyst?) - Job Description As the Application Security Engineer (Analyst) at the Information Security team, you will support security analysis and security support activities into softwa…",
            "company": {
                "display_name": "KPG99 INC",
                "__CLASS__": "Adzuna::API::Response::Company"
            },
            "title": "Application Security Engineer (SAST, SCA, DAST) - Offshore",
            "location": {
                "display_name": "India",
                "area": [
                    "India"
                ],
                "__CLASS__": "Adzuna::API::Response::Location"
            },
            "__CLASS__": "Adzuna::API::Response::Job",
            "salary_is_predicted": "0",
            "redirect_url": "https://www.adzuna.in/land/ad/5549497891?se=SlJrXFji8BGjJabxWt0eDQ&utm_medium=api&utm_source=d58ac19b&v=D6DAE826674788961605FC5C17265CFD5C5A183F",
            "category": {
                "tag": "it-jobs",
                "__CLASS__": "Adzuna::API::Response::Category",
                "label": "IT Jobs"
            }
        },
        {
            "__CLASS__": "Adzuna::API::Response::Job",
            "location": {
                "display_name": "Bangalore, Karnataka",
                "area": [
                    "India",
                    "Karnataka",
                    "Bangalore"
                ],
                "__CLASS__": "Adzuna::API::Response::Location"
            },
            "redirect_url": "https://www.adzuna.in/land/ad/5523454158?se=SlJrXFji8BGjJabxWt0eDQ&utm_medium=api&utm_source=d58ac19b&v=B505F462847872C3240566A234511ECAE190C7E2",
            "category": {
                "label": "IT Jobs",
                "tag": "it-jobs",
                "__CLASS__": "Adzuna::API::Response::Category"
            },
            "salary_is_predicted": "0",
            "description": "Greetings from Tata Consultancy Services We are hiring Java, Spring and AWS Developer ! Position: Java, Spring and AWS Developer Job Location: Bangalore Experience : 7-15 years Interested professionals kindly apply through the link. Must Have: Experience in web application development or software engineering in a large enterprise environment using Java , Spring Boot , and AWS . Familiarity with cloud-native storage and compute technologies in AWS (e.g., S3 , Lambda , EC2 , ECS , EKS ). Experien…",
            "company": {
                "__CLASS__": "Adzuna::API::Response::Company",
                "display_name": "Tata Consultancy Services"
            },
            "id": "5523454158",
            "created": "2025-12-02T08:53:56Z",
            "adref": "eyJhbGciOiJIUzI1NiJ9.eyJzIjoiU2xKclhGamk4QkdqSmFieFd0MGVEUSIsImkiOiI1NTIzNDU0MTU4In0.I9Y5OG2lT1YraUpycr-SpIDkCdIIj9FvKbUh5jFXj-M",
            "title": "Java, Spring and AWS Developer"
        },
        {
            "title": "Frontend Developer",
            "id": "5556102993",
            "company": {
                "display_name": "Vasu Travel & Tourism LLC",
                "__CLASS__": "Adzuna::API::Response::Company"
            },
            "description": "Company Description Vasu Travel & Tourism LLC specializes in delivering comprehensive travel solutions, catering to both B2B and B2C clients. The company provides competitive travel tickets, visa assistance, and reliable transfer services to ensure smooth and hassle-free travel experiences. With a dedicated team offering round-the-clock support and personalized services, Vasu Travel & Tourism LLC addresses diverse travel requirements, whether for corporate or personal trips. Visit https://vasut…",
            "adref": "eyJhbGciOiJIUzI1NiJ9.eyJpIjoiNTU1NjEwMjk5MyIsInMiOiJTbEpyWEZqaThCR2pKYWJ4V3QwZURRIn0.fMVXpgzzXVlxw_xHYaUQQySqOHZENjuZ08wcZOe3odM",
            "contract_time": "full_time",
            "created": "2025-12-26T08:36:42Z",
            "category": {
                "label": "IT Jobs",
                "tag": "it-jobs",
                "__CLASS__": "Adzuna::API::Response::Category"
            },
            "redirect_url": "https://www.adzuna.in/land/ad/5556102993?se=SlJrXFji8BGjJabxWt0eDQ&utm_medium=api&utm_source=d58ac19b&v=6608C6D4B8FD4EA7BCF468F4498C85BBDA380CCB",
            "salary_is_predicted": "0",
            "location": {
                "__CLASS__": "Adzuna::API::Response::Location",
                "display_name": "India",
                "area": [
                    "India"
                ]
            },
            "__CLASS__": "Adzuna::API::Response::Job"
        },
        {
            "title": "Software Engineer - Web",
            "adref": "eyJhbGciOiJIUzI1NiJ9.eyJzIjoiU2xKclhGamk4QkdqSmFieFd0MGVEUSIsImkiOiI0ODAxNjM0MzIxIn0.17unfHbQZ-MQYHkvc0j5B_G-a4zBYDuEXb_V-K__8JA",
            "created": "2024-07-31T03:20:09Z",
            "id": "4801634321",
            "company": {
                "display_name": "Heckyl",
                "__CLASS__": "Adzuna::API::Response::Company"
            },
            "longitude": 72.84415,
            "description": "Are you a Senior Web Engineer who's looking to join a company whose DNA is innovation and believes he can make a difference? If so, we think we've got the opportunity you're looking for. As a Senior Web Engineer, you've faced big challenges in building beautiful, easy to use, highly scaleable web applications that service hundreds of thousands or millions of users. Qualification 3 - 5 years experience in Microsoft Dot Net Technologies",
            "salary_is_predicted": "0",
            "redirect_url": "https://www.adzuna.in/details/4801634321?utm_medium=api&utm_source=d58ac19b",
            "category": {
                "label": "IT Jobs",
                "tag": "it-jobs",
                "__CLASS__": "Adzuna::API::Response::Category"
            },
            "latitude": 19.00821,
            "location": {
                "__CLASS__": "Adzuna::API::Response::Location",
                "area": [
                    "India",
                    "Maharashtra",
                    "Mumbai"
                ],
                "display_name": "Mumbai, Maharashtra"
            },
            "__CLASS__": "Adzuna::API::Response::Job"
        },
        {
            "id": "5539801852",
            "longitude": 77.59837,
            "company": {
                "__CLASS__": "Adzuna::API::Response::Company",
                "display_name": "StockX"
            },
            "description": "Help empower our global customers to connect to culture through their passions. Why You’ll Love This Role As a Software Engineer, you will be empowered to take ownership of technology decisions and solutions while playing a pivotal role in establishing a successful engineering culture at a fast-growing company. This is a great opportunity to leverage your existing skills, to be part of a world-class team, and to have a huge impact on how marketplaces can be redefined.Our web technical stack com…",
            "created": "2025-12-13T00:12:01Z",
            "adref": "eyJhbGciOiJIUzI1NiJ9.eyJzIjoiU2xKclhGamk4QkdqSmFieFd0MGVEUSIsImkiOiI1NTM5ODAxODUyIn0.AWIawIwHM1Hd3ePhFe594eMWcSVmk5nVo9LU7ZhGNdo",
            "title": "Software Engineer-Web",
            "location": {
                "area": [
                    "India",
                    "Karnataka",
                    "Bangalore"
                ],
                "display_name": "Bangalore, Karnataka",
                "__CLASS__": "Adzuna::API::Response::Location"
            },
            "__CLASS__": "Adzuna::API::Response::Job",
            "latitude": 12.95703,
            "redirect_url": "https://www.adzuna.in/details/5539801852?utm_medium=api&utm_source=d58ac19b",
            "category": {
                "tag": "engineering-jobs",
                "__CLASS__": "Adzuna::API::Response::Category",
                "label": "Engineering Jobs"
            },
            "salary_is_predicted": "0"
        }
    ],
    "count": 961,
    "__CLASS__": "Adzuna::API::Response::JobSearchResults"
}